{
  "conceptnet": {
    "related_terms": {
      "paralysis": {
        "@id": "/a/[/r/RelatedTo/,/c/en/paralysis/n/,/c/en/quadriplegia/]",
        "weight": 1.0,
        "start": {
          "@id": "/c/en/paralysis/n",
          "@type": "Node",
          "label": "paralysis",
          "language": "en",
          "sense_label": "n",
          "term": "/c/en/paralysis"
        },
        "end": {
          "@id": "/c/en/quadriplegia",
          "@type": "Node",
          "label": "quadriplegia",
          "language": "en",
          "term": "/c/en/quadriplegia"
        }
      },
      "quadriplegias": {
        "@id": "/a/[/r/RelatedTo/,/c/en/quadriplegias/n/,/c/en/quadriplegia/]",
        "weight": 1.0,
        "start": {
          "@id": "/c/en/quadriplegias/n",
          "@type": "Node",
          "label": "quadriplegias",
          "language": "en",
          "sense_label": "n",
          "term": "/c/en/quadriplegias"
        },
        "end": {
          "@id": "/c/en/quadriplegia",
          "@type": "Node",
          "label": "quadriplegia",
          "language": "en",
          "term": "/c/en/quadriplegia"
        }
      },
      "quadriplegic": {
        "@id": "/a/[/r/RelatedTo/,/c/en/quadriplegic/n/,/c/en/quadriplegia/]",
        "weight": 1.0,
        "start": {
          "@id": "/c/en/quadriplegic/n",
          "@type": "Node",
          "label": "quadriplegic",
          "language": "en",
          "sense_label": "n",
          "term": "/c/en/quadriplegic"
        },
        "end": {
          "@id": "/c/en/quadriplegia",
          "@type": "Node",
          "label": "quadriplegia",
          "language": "en",
          "term": "/c/en/quadriplegia"
        }
      },
      "paraplegia": {
        "@id": "/a/[/r/RelatedTo/,/c/en/paraplegia/n/,/c/en/quadriplegia/]",
        "weight": 1.0,
        "start": {
          "@id": "/c/en/paraplegia/n",
          "@type": "Node",
          "label": "paraplegia",
          "language": "en",
          "sense_label": "n",
          "term": "/c/en/paraplegia"
        },
        "end": {
          "@id": "/c/en/quadriplegia",
          "@type": "Node",
          "label": "quadriplegia",
          "language": "en",
          "term": "/c/en/quadriplegia"
        }
      },
      "neck": {
        "@id": "/a/[/r/RelatedTo/,/c/en/quadriplegia/n/,/c/en/neck/]",
        "weight": 1.0,
        "start": {
          "@id": "/c/en/quadriplegia/n",
          "@type": "Node",
          "label": "quadriplegia",
          "language": "en",
          "sense_label": "n",
          "term": "/c/en/quadriplegia"
        },
        "end": {
          "@id": "/c/en/neck",
          "@type": "Node",
          "label": "neck",
          "language": "en",
          "term": "/c/en/neck"
        }
      },
      "limb": {
        "@id": "/a/[/r/RelatedTo/,/c/en/quadriplegia/n/,/c/en/limb/]",
        "weight": 1.0,
        "start": {
          "@id": "/c/en/quadriplegia/n",
          "@type": "Node",
          "label": "quadriplegia",
          "language": "en",
          "sense_label": "n",
          "term": "/c/en/quadriplegia"
        },
        "end": {
          "@id": "/c/en/limb",
          "@type": "Node",
          "label": "limb",
          "language": "en",
          "term": "/c/en/limb"
        }
      }
    },
    "distinct_terms": {},
    "synonyms": {
      "tetraplegia": {
        "@id": "/a/[/r/Synonym/,/c/en/quadriplegia/n/,/c/en/tetraplegia/]",
        "weight": 1.0,
        "start": {
          "@id": "/c/en/quadriplegia/n",
          "@type": "Node",
          "label": "quadriplegia",
          "language": "en",
          "sense_label": "n",
          "term": "/c/en/quadriplegia"
        },
        "end": {
          "@id": "/c/en/tetraplegia",
          "@type": "Node",
          "label": "tetraplegia",
          "language": "en",
          "term": "/c/en/tetraplegia"
        }
      }
    },
    "antonyms": {},
    "similar_terms": {},
    "word_forms": {
      "quadriplegias": {
        "@id": "/a/[/r/FormOf/,/c/en/quadriplegias/n/,/c/en/quadriplegia/]",
        "weight": 1.0,
        "start": {
          "@id": "/c/en/quadriplegias/n",
          "@type": "Node",
          "label": "quadriplegias",
          "language": "en",
          "sense_label": "n",
          "term": "/c/en/quadriplegias"
        },
        "end": {
          "@id": "/c/en/quadriplegia",
          "@type": "Node",
          "label": "quadriplegia",
          "language": "en",
          "term": "/c/en/quadriplegia"
        }
      }
    }
  },
  "relatedwords": {
    "paraplegia": {
      "data-frequency": "816",
      "data-relevance": "222",
      "data-term": "paraplegia",
      "data-encoded-term": "paraplegia",
      "data-term-stats": [
        "1",
        "4.8",
        "0.000",
        "816",
        "ol,w2v,wiki",
        "1"
      ]
    },
    "tetraplegia": {
      "data-frequency": "191",
      "data-relevance": "221",
      "data-term": "tetraplegia",
      "data-encoded-term": "tetraplegia",
      "data-term-stats": [
        "1",
        "1.4",
        "0.000",
        "191",
        "ol,w2v",
        "1"
      ]
    },
    "paralysis": {
      "data-frequency": "6682",
      "data-relevance": "220",
      "data-term": "paralysis",
      "data-encoded-term": "paralysis",
      "data-term-stats": [
        "1",
        "5.2",
        "0.000",
        "6682",
        "ol,wiki,wn",
        "1"
      ]
    },
    "palsy": {
      "data-frequency": "4023",
      "data-relevance": "219",
      "data-term": "palsy",
      "data-encoded-term": "palsy",
      "data-term-stats": [
        "1",
        "1.9",
        "0.000",
        "4023",
        "ol,wn",
        "1"
      ]
    },
    "spastic": {
      "data-frequency": "779",
      "data-relevance": "218",
      "data-term": "spastic",
      "data-encoded-term": "spastic",
      "data-term-stats": [
        "1",
        "1.8",
        "0.000",
        "779",
        "ol,w2v",
        "1"
      ]
    },
    "hemiplegia": {
      "data-frequency": "337",
      "data-relevance": "217",
      "data-term": "hemiplegia",
      "data-encoded-term": "hemiplegia",
      "data-term-stats": [
        "1",
        "1.5",
        "0.000",
        "337",
        "ol,w2v",
        "1"
      ]
    },
    "achondroplasia": {
      "data-frequency": "139",
      "data-relevance": "216",
      "data-term": "achondroplasia",
      "data-encoded-term": "achondroplasia",
      "data-term-stats": [
        "1",
        "1.5",
        "0.000",
        "139",
        "ol,w2v",
        "1"
      ]
    },
    "dysgraphia": {
      "data-frequency": "79",
      "data-relevance": "215",
      "data-term": "dysgraphia",
      "data-encoded-term": "dysgraphia",
      "data-term-stats": [
        "1",
        "1.4",
        "0.000",
        "79",
        "ol,w2v",
        "1"
      ]
    },
    "empyema": {
      "data-frequency": "255",
      "data-relevance": "214",
      "data-term": "empyema",
      "data-encoded-term": "empyema",
      "data-term-stats": [
        "1",
        "1.3",
        "0.000",
        "255",
        "ol,w2v",
        "1"
      ]
    },
    "torso": {
      "data-frequency": "5623",
      "data-relevance": "213",
      "data-term": "torso",
      "data-encoded-term": "torso",
      "data-term-stats": [
        "1",
        "0.7",
        "0.000",
        "5623",
        "wiki",
        "1"
      ]
    },
    "cerebral palsy": {
      "data-frequency": "2941",
      "data-relevance": "212",
      "data-term": "cerebral palsy",
      "data-encoded-term": "cerebral%20palsy",
      "data-term-stats": [
        "1",
        "0.6",
        "0.000",
        "2941",
        "ol,wiki",
        "1"
      ]
    },
    "multiple sclerosis": {
      "data-frequency": "3414",
      "data-relevance": "211",
      "data-term": "multiple sclerosis",
      "data-encoded-term": "multiple%20sclerosis",
      "data-term-stats": [
        "1",
        "0.6",
        "0.000",
        "3414",
        "ol,wiki",
        "1"
      ]
    },
    "congenital disorder": {
      "data-frequency": "426",
      "data-relevance": "210",
      "data-term": "congenital disorder",
      "data-encoded-term": "congenital%20disorder",
      "data-term-stats": [
        "1",
        "0.6",
        "0.000",
        "426",
        "ol,wiki",
        "1"
      ]
    },
    "muscular dystrophy": {
      "data-frequency": "1255",
      "data-relevance": "209",
      "data-term": "muscular dystrophy",
      "data-encoded-term": "muscular%20dystrophy",
      "data-term-stats": [
        "1",
        "0.6",
        "0.000",
        "1255",
        "ol,wiki",
        "1"
      ]
    },
    "osteoporosis": {
      "data-frequency": "1421",
      "data-relevance": "208",
      "data-term": "osteoporosis",
      "data-encoded-term": "osteoporosis",
      "data-term-stats": [
        "1",
        "0.5",
        "0.000",
        "1421",
        "wiki",
        "1"
      ]
    },
    "neuralgia": {
      "data-frequency": "603",
      "data-relevance": "207",
      "data-term": "neuralgia",
      "data-encoded-term": "neuralgia",
      "data-term-stats": [
        "1",
        "0.6",
        "0.000",
        "603",
        "wiki",
        "1"
      ]
    },
    "proportioning": {
      "data-frequency": "112",
      "data-relevance": "206",
      "data-term": "proportioning",
      "data-encoded-term": "proportioning",
      "data-term-stats": [
        "1",
        "0.5",
        "0.000",
        "112",
        "w2v",
        "1"
      ]
    },
    "purulent": {
      "data-frequency": "193",
      "data-relevance": "205",
      "data-term": "purulent",
      "data-encoded-term": "purulent",
      "data-term-stats": [
        "1",
        "0.5",
        "0.000",
        "193",
        "w2v",
        "1"
      ]
    },
    "laterals": {
      "data-frequency": "426",
      "data-relevance": "204",
      "data-term": "laterals",
      "data-encoded-term": "laterals",
      "data-term-stats": [
        "1",
        "0.5",
        "0.000",
        "426",
        "w2v",
        "1"
      ]
    },
    "ruotsalainen": {
      "data-frequency": "314",
      "data-relevance": "203",
      "data-term": "ruotsalainen",
      "data-encoded-term": "ruotsalainen",
      "data-term-stats": [
        "1",
        "0.5",
        "0.000",
        "314",
        "w2v",
        "1"
      ]
    },
    "spasticity": {
      "data-frequency": "482",
      "data-relevance": "202",
      "data-term": "spasticity",
      "data-encoded-term": "spasticity",
      "data-term-stats": [
        "1",
        "0.5",
        "0.000",
        "482",
        "wiki",
        "1"
      ]
    },
    "dwarfism": {
      "data-frequency": "1249",
      "data-relevance": "201",
      "data-term": "dwarfism",
      "data-encoded-term": "dwarfism",
      "data-term-stats": [
        "1",
        "0.5",
        "0.000",
        "1249",
        "w2v",
        "1"
      ]
    },
    "kimon": {
      "data-frequency": "412",
      "data-relevance": "200",
      "data-term": "kimon",
      "data-encoded-term": "kimon",
      "data-term-stats": [
        "1",
        "0.5",
        "0.000",
        "412",
        "w2v",
        "1"
      ]
    },
    "kaarina": {
      "data-frequency": "385",
      "data-relevance": "199",
      "data-term": "kaarina",
      "data-encoded-term": "kaarina",
      "data-term-stats": [
        "1",
        "0.5",
        "0.000",
        "385",
        "w2v",
        "1"
      ]
    },
    "scalds": {
      "data-frequency": "601",
      "data-relevance": "198",
      "data-term": "scalds",
      "data-encoded-term": "scalds",
      "data-term-stats": [
        "1",
        "0.5",
        "0.000",
        "601",
        "w2v",
        "1"
      ]
    },
    "hemorrhoids": {
      "data-frequency": "299",
      "data-relevance": "197",
      "data-term": "hemorrhoids",
      "data-encoded-term": "hemorrhoids",
      "data-term-stats": [
        "1",
        "0.5",
        "0.000",
        "299",
        "w2v",
        "1"
      ]
    },
    "lumbago": {
      "data-frequency": "131",
      "data-relevance": "196",
      "data-term": "lumbago",
      "data-encoded-term": "lumbago",
      "data-term-stats": [
        "1",
        "0.5",
        "0.000",
        "131",
        "w2v",
        "1"
      ]
    },
    "inadvertence": {
      "data-frequency": "65",
      "data-relevance": "195",
      "data-term": "inadvertence",
      "data-encoded-term": "inadvertence",
      "data-term-stats": [
        "1",
        "0.5",
        "0.000",
        "65",
        "w2v",
        "1"
      ]
    },
    "consequentially": {
      "data-frequency": "2654",
      "data-relevance": "194",
      "data-term": "consequentially",
      "data-encoded-term": "consequentially",
      "data-term-stats": [
        "1",
        "0.5",
        "0.000",
        "2654",
        "w2v",
        "1"
      ]
    },
    "rivetted": {
      "data-frequency": "4105",
      "data-relevance": "193",
      "data-term": "rivetted",
      "data-encoded-term": "rivetted",
      "data-term-stats": [
        "1",
        "0.5",
        "0.000",
        "4105",
        "w2v",
        "1"
      ]
    },
    "burdening": {
      "data-frequency": "25493",
      "data-relevance": "192",
      "data-term": "burdening",
      "data-encoded-term": "burdening",
      "data-term-stats": [
        "1",
        "0.5",
        "0.000",
        "25493",
        "w2v",
        "1"
      ]
    },
    "diaphragmatic": {
      "data-frequency": "507",
      "data-relevance": "191",
      "data-term": "diaphragmatic",
      "data-encoded-term": "diaphragmatic",
      "data-term-stats": [
        "1",
        "0.5",
        "0.000",
        "507",
        "w2v",
        "1"
      ]
    },
    "disapprobation": {
      "data-frequency": "117",
      "data-relevance": "190",
      "data-term": "disapprobation",
      "data-encoded-term": "disapprobation",
      "data-term-stats": [
        "1",
        "0.5",
        "0.000",
        "117",
        "w2v",
        "1"
      ]
    },
    "pavlović": {
      "data-frequency": "2687",
      "data-relevance": "189",
      "data-term": "pavlović",
      "data-encoded-term": "pavlovi%C4%87",
      "data-term-stats": [
        "1",
        "0.5",
        "0.000",
        "2687",
        "w2v",
        "1"
      ]
    },
    "bedsore": {
      "data-frequency": "-1",
      "data-relevance": "188",
      "data-term": "bedsore",
      "data-encoded-term": "bedsore",
      "data-term-stats": [
        "1",
        "0.5",
        "0.000",
        "-1",
        "wiki",
        "1"
      ]
    },
    "diplegia": {
      "data-frequency": "59",
      "data-relevance": "187",
      "data-term": "diplegia",
      "data-encoded-term": "diplegia",
      "data-term-stats": [
        "1",
        "0.5",
        "0.000",
        "59",
        "w2v",
        "1"
      ]
    },
    "flaccid paralysis": {
      "data-frequency": "96",
      "data-relevance": "186",
      "data-term": "flaccid paralysis",
      "data-encoded-term": "flaccid%20paralysis",
      "data-term-stats": [
        "1",
        "0.4",
        "0.000",
        "96",
        "wiki",
        "1"
      ]
    },
    "achromatopsia": {
      "data-frequency": "277",
      "data-relevance": "185",
      "data-term": "achromatopsia",
      "data-encoded-term": "achromatopsia",
      "data-term-stats": [
        "1",
        "0.4",
        "0.000",
        "277",
        "w2v",
        "1"
      ]
    },
    "spastic quadriplegia": {
      "data-frequency": "-1",
      "data-relevance": "184",
      "data-term": "spastic quadriplegia",
      "data-encoded-term": "spastic%20quadriplegia",
      "data-term-stats": [
        "1",
        "0.4",
        "0.000",
        "-1",
        "wiki",
        "1"
      ]
    },
    "autoregulation": {
      "data-frequency": "129",
      "data-relevance": "183",
      "data-term": "autoregulation",
      "data-encoded-term": "autoregulation",
      "data-term-stats": [
        "1",
        "0.4",
        "0.000",
        "129",
        "w2v",
        "1"
      ]
    },
    "ventilator": {
      "data-frequency": "1191",
      "data-relevance": "182",
      "data-term": "ventilator",
      "data-encoded-term": "ventilator",
      "data-term-stats": [
        "1",
        "0.4",
        "0.000",
        "1191",
        "wiki",
        "1"
      ]
    },
    "ulmann": {
      "data-frequency": "150",
      "data-relevance": "181",
      "data-term": "ulmann",
      "data-encoded-term": "ulmann",
      "data-term-stats": [
        "1",
        "0.4",
        "0.000",
        "150",
        "w2v",
        "1"
      ]
    },
    "ataxic": {
      "data-frequency": "100",
      "data-relevance": "180",
      "data-term": "ataxic",
      "data-encoded-term": "ataxic",
      "data-term-stats": [
        "1",
        "0.4",
        "0.000",
        "100",
        "w2v",
        "1"
      ]
    },
    "pröll": {
      "data-frequency": "275",
      "data-relevance": "179",
      "data-term": "pröll",
      "data-encoded-term": "pr%C3%B6ll",
      "data-term-stats": [
        "1",
        "0.4",
        "0.000",
        "275",
        "w2v",
        "1"
      ]
    },
    "kugimiya": {
      "data-frequency": "351",
      "data-relevance": "178",
      "data-term": "kugimiya",
      "data-encoded-term": "kugimiya",
      "data-term-stats": [
        "1",
        "0.4",
        "0.000",
        "351",
        "w2v",
        "1"
      ]
    },
    "khoya": {
      "data-frequency": "175",
      "data-relevance": "177",
      "data-term": "khoya",
      "data-encoded-term": "khoya",
      "data-term-stats": [
        "1",
        "0.4",
        "0.000",
        "175",
        "w2v",
        "1"
      ]
    },
    "pasquel": {
      "data-frequency": "170",
      "data-relevance": "176",
      "data-term": "pasquel",
      "data-encoded-term": "pasquel",
      "data-term-stats": [
        "1",
        "0.4",
        "0.000",
        "170",
        "w2v",
        "1"
      ]
    },
    "disfigurements": {
      "data-frequency": "3314",
      "data-relevance": "175",
      "data-term": "disfigurements",
      "data-encoded-term": "disfigurements",
      "data-term-stats": [
        "1",
        "0.4",
        "0.000",
        "3314",
        "w2v",
        "1"
      ]
    },
    "hypoperfusion": {
      "data-frequency": "82",
      "data-relevance": "174",
      "data-term": "hypoperfusion",
      "data-encoded-term": "hypoperfusion",
      "data-term-stats": [
        "1",
        "0.4",
        "0.000",
        "82",
        "w2v",
        "1"
      ]
    },
    "stimulations": {
      "data-frequency": "27498",
      "data-relevance": "173",
      "data-term": "stimulations",
      "data-encoded-term": "stimulations",
      "data-term-stats": [
        "1",
        "0.4",
        "0.000",
        "27498",
        "w2v",
        "1"
      ]
    },
    "tzvetan": {
      "data-frequency": "145",
      "data-relevance": "172",
      "data-term": "tzvetan",
      "data-encoded-term": "tzvetan",
      "data-term-stats": [
        "1",
        "0.4",
        "0.000",
        "145",
        "w2v",
        "1"
      ]
    },
    "obba": {
      "data-frequency": "157",
      "data-relevance": "171",
      "data-term": "obba",
      "data-encoded-term": "obba",
      "data-term-stats": [
        "1",
        "0.4",
        "0.000",
        "157",
        "w2v",
        "1"
      ]
    },
    "roughening": {
      "data-frequency": "76",
      "data-relevance": "170",
      "data-term": "roughening",
      "data-encoded-term": "roughening",
      "data-term-stats": [
        "1",
        "0.4",
        "0.000",
        "76",
        "w2v",
        "1"
      ]
    },
    "turgay": {
      "data-frequency": "318",
      "data-relevance": "169",
      "data-term": "turgay",
      "data-encoded-term": "turgay",
      "data-term-stats": [
        "1",
        "0.4",
        "0.000",
        "318",
        "w2v",
        "1"
      ]
    },
    "lefter": {
      "data-frequency": "651303",
      "data-relevance": "168",
      "data-term": "lefter",
      "data-encoded-term": "lefter",
      "data-term-stats": [
        "1",
        "0.4",
        "0.000",
        "651303",
        "w2v",
        "1"
      ]
    },
    "tereshchenko": {
      "data-frequency": "238",
      "data-relevance": "167",
      "data-term": "tereshchenko",
      "data-encoded-term": "tereshchenko",
      "data-term-stats": [
        "1",
        "0.4",
        "0.000",
        "238",
        "w2v",
        "1"
      ]
    },
    "gospodinov": {
      "data-frequency": "158",
      "data-relevance": "166",
      "data-term": "gospodinov",
      "data-encoded-term": "gospodinov",
      "data-term-stats": [
        "1",
        "0.4",
        "0.000",
        "158",
        "w2v",
        "1"
      ]
    },
    "tetherball": {
      "data-frequency": "68",
      "data-relevance": "165",
      "data-term": "tetherball",
      "data-encoded-term": "tetherball",
      "data-term-stats": [
        "1",
        "0.4",
        "0.000",
        "68",
        "w2v",
        "1"
      ]
    },
    "spanakopita": {
      "data-frequency": "378",
      "data-relevance": "164",
      "data-term": "spanakopita",
      "data-encoded-term": "spanakopita",
      "data-term-stats": [
        "1",
        "0.4",
        "0.000",
        "378",
        "w2v",
        "1"
      ]
    },
    "melikyan": {
      "data-frequency": "134",
      "data-relevance": "163",
      "data-term": "melikyan",
      "data-encoded-term": "melikyan",
      "data-term-stats": [
        "1",
        "0.4",
        "0.000",
        "134",
        "w2v",
        "1"
      ]
    },
    "auricles": {
      "data-frequency": "133",
      "data-relevance": "162",
      "data-term": "auricles",
      "data-encoded-term": "auricles",
      "data-term-stats": [
        "1",
        "0.4",
        "0.000",
        "133",
        "w2v",
        "1"
      ]
    },
    "semi-feudal": {
      "data-frequency": "131",
      "data-relevance": "161",
      "data-term": "semi-feudal",
      "data-encoded-term": "semi-feudal",
      "data-term-stats": [
        "1",
        "0.4",
        "0.000",
        "131",
        "w2v",
        "1"
      ]
    },
    "naegeli": {
      "data-frequency": "103",
      "data-relevance": "160",
      "data-term": "naegeli",
      "data-encoded-term": "naegeli",
      "data-term-stats": [
        "1",
        "0.4",
        "0.000",
        "103",
        "w2v",
        "1"
      ]
    },
    "bērziņš": {
      "data-frequency": "380",
      "data-relevance": "159",
      "data-term": "bērziņš",
      "data-encoded-term": "b%C4%93rzi%C5%86%C5%A1",
      "data-term-stats": [
        "1",
        "0.4",
        "0.000",
        "380",
        "w2v",
        "1"
      ]
    },
    "földes": {
      "data-frequency": "59008",
      "data-relevance": "158",
      "data-term": "földes",
      "data-encoded-term": "f%C3%B6ldes",
      "data-term-stats": [
        "1",
        "0.4",
        "0.000",
        "59008",
        "w2v",
        "1"
      ]
    },
    "unbridged": {
      "data-frequency": "71",
      "data-relevance": "157",
      "data-term": "unbridged",
      "data-encoded-term": "unbridged",
      "data-term-stats": [
        "1",
        "0.4",
        "0.000",
        "71",
        "w2v",
        "1"
      ]
    },
    "honório": {
      "data-frequency": "1167",
      "data-relevance": "156",
      "data-term": "honório",
      "data-encoded-term": "hon%C3%B3rio",
      "data-term-stats": [
        "1",
        "0.4",
        "0.000",
        "1167",
        "w2v",
        "1"
      ]
    },
    "1975-1981": {
      "data-frequency": "142049",
      "data-relevance": "155",
      "data-term": "1975-1981",
      "data-encoded-term": "1975-1981",
      "data-term-stats": [
        "1",
        "0.4",
        "0.000",
        "142049",
        "w2v",
        "1"
      ]
    },
    "bagirov": {
      "data-frequency": "158",
      "data-relevance": "154",
      "data-term": "bagirov",
      "data-encoded-term": "bagirov",
      "data-term-stats": [
        "1",
        "0.4",
        "0.000",
        "158",
        "w2v",
        "1"
      ]
    },
    "kārlis": {
      "data-frequency": "1440",
      "data-relevance": "153",
      "data-term": "kārlis",
      "data-encoded-term": "k%C4%81rlis",
      "data-term-stats": [
        "1",
        "0.4",
        "0.000",
        "1440",
        "w2v",
        "1"
      ]
    },
    "brain": {
      "data-frequency": "68164",
      "data-relevance": "152",
      "data-term": "brain",
      "data-encoded-term": "brain",
      "data-term-stats": [
        "1",
        "0.4",
        "0.000",
        "68164",
        "wiki",
        "1"
      ]
    },
    "murakawa": {
      "data-frequency": "422",
      "data-relevance": "151",
      "data-term": "murakawa",
      "data-encoded-term": "murakawa",
      "data-term-stats": [
        "1",
        "0.4",
        "0.000",
        "422",
        "w2v",
        "1"
      ]
    },
    "köksal": {
      "data-frequency": "326",
      "data-relevance": "150",
      "data-term": "köksal",
      "data-encoded-term": "k%C3%B6ksal",
      "data-term-stats": [
        "1",
        "0.4",
        "0.000",
        "326",
        "w2v",
        "1"
      ]
    },
    "takiguchi": {
      "data-frequency": "251",
      "data-relevance": "149",
      "data-term": "takiguchi",
      "data-encoded-term": "takiguchi",
      "data-term-stats": [
        "1",
        "0.4",
        "0.000",
        "251",
        "w2v",
        "1"
      ]
    },
    "phlebitis": {
      "data-frequency": "289",
      "data-relevance": "148",
      "data-term": "phlebitis",
      "data-encoded-term": "phlebitis",
      "data-term-stats": [
        "1",
        "0.4",
        "0.000",
        "289",
        "w2v",
        "1"
      ]
    },
    "pigmentary": {
      "data-frequency": "130",
      "data-relevance": "147",
      "data-term": "pigmentary",
      "data-encoded-term": "pigmentary",
      "data-term-stats": [
        "1",
        "0.4",
        "0.000",
        "130",
        "w2v",
        "1"
      ]
    },
    "panpipes": {
      "data-frequency": "165",
      "data-relevance": "146",
      "data-term": "panpipes",
      "data-encoded-term": "panpipes",
      "data-term-stats": [
        "1",
        "0.4",
        "0.000",
        "165",
        "w2v",
        "1"
      ]
    },
    "overexertion": {
      "data-frequency": "131",
      "data-relevance": "145",
      "data-term": "overexertion",
      "data-encoded-term": "overexertion",
      "data-term-stats": [
        "1",
        "0.4",
        "0.000",
        "131",
        "w2v",
        "1"
      ]
    },
    "pashutin": {
      "data-frequency": "91",
      "data-relevance": "144",
      "data-term": "pashutin",
      "data-encoded-term": "pashutin",
      "data-term-stats": [
        "1",
        "0.4",
        "0.000",
        "91",
        "w2v",
        "1"
      ]
    },
    "epistaxis": {
      "data-frequency": "123",
      "data-relevance": "143",
      "data-term": "epistaxis",
      "data-encoded-term": "epistaxis",
      "data-term-stats": [
        "1",
        "0.4",
        "0.000",
        "123",
        "w2v",
        "1"
      ]
    },
    "hyperinsulinism": {
      "data-frequency": "224",
      "data-relevance": "142",
      "data-term": "hyperinsulinism",
      "data-encoded-term": "hyperinsulinism",
      "data-term-stats": [
        "1",
        "0.4",
        "0.000",
        "224",
        "w2v",
        "1"
      ]
    },
    "somogyi": {
      "data-frequency": "507",
      "data-relevance": "141",
      "data-term": "somogyi",
      "data-encoded-term": "somogyi",
      "data-term-stats": [
        "1",
        "0.4",
        "0.000",
        "507",
        "w2v",
        "1"
      ]
    },
    "chacín": {
      "data-frequency": "310",
      "data-relevance": "140",
      "data-term": "chacín",
      "data-encoded-term": "chac%C3%ADn",
      "data-term-stats": [
        "1",
        "0.4",
        "0.000",
        "310",
        "w2v",
        "1"
      ]
    },
    "kantorovich": {
      "data-frequency": "149",
      "data-relevance": "139",
      "data-term": "kantorovich",
      "data-encoded-term": "kantorovich",
      "data-term-stats": [
        "1",
        "0.4",
        "0.000",
        "149",
        "w2v",
        "1"
      ]
    },
    "geneti": {
      "data-frequency": "-1",
      "data-relevance": "138",
      "data-term": "geneti",
      "data-encoded-term": "geneti",
      "data-term-stats": [
        "1",
        "0.4",
        "0.000",
        "-1",
        "w2v",
        "1"
      ]
    },
    "marasmus": {
      "data-frequency": "74",
      "data-relevance": "137",
      "data-term": "marasmus",
      "data-encoded-term": "marasmus",
      "data-term-stats": [
        "1",
        "0.4",
        "0.000",
        "74",
        "w2v",
        "1"
      ]
    },
    "saygin": {
      "data-frequency": "79",
      "data-relevance": "136",
      "data-term": "saygin",
      "data-encoded-term": "saygin",
      "data-term-stats": [
        "1",
        "0.4",
        "0.000",
        "79",
        "w2v",
        "1"
      ]
    },
    "orekhov": {
      "data-frequency": "248",
      "data-relevance": "135",
      "data-term": "orekhov",
      "data-encoded-term": "orekhov",
      "data-term-stats": [
        "1",
        "0.4",
        "0.000",
        "248",
        "w2v",
        "1"
      ]
    },
    "andrianov": {
      "data-frequency": "203",
      "data-relevance": "134",
      "data-term": "andrianov",
      "data-encoded-term": "andrianov",
      "data-term-stats": [
        "1",
        "0.4",
        "0.000",
        "203",
        "w2v",
        "1"
      ]
    },
    "anti-icing": {
      "data-frequency": "100",
      "data-relevance": "133",
      "data-term": "anti-icing",
      "data-encoded-term": "anti-icing",
      "data-term-stats": [
        "1",
        "0.4",
        "0.000",
        "100",
        "w2v",
        "1"
      ]
    },
    "low-flow": {
      "data-frequency": "522",
      "data-relevance": "132",
      "data-term": "low-flow",
      "data-encoded-term": "low-flow",
      "data-term-stats": [
        "1",
        "0.4",
        "0.000",
        "522",
        "w2v",
        "1"
      ]
    },
    "kestutis": {
      "data-frequency": "560",
      "data-relevance": "131",
      "data-term": "kestutis",
      "data-encoded-term": "kestutis",
      "data-term-stats": [
        "1",
        "0.4",
        "0.000",
        "560",
        "w2v",
        "1"
      ]
    },
    "bidault": {
      "data-frequency": "396",
      "data-relevance": "130",
      "data-term": "bidault",
      "data-encoded-term": "bidault",
      "data-term-stats": [
        "1",
        "0.4",
        "0.000",
        "396",
        "w2v",
        "1"
      ]
    },
    "yiannopoulos": {
      "data-frequency": "159",
      "data-relevance": "129",
      "data-term": "yiannopoulos",
      "data-encoded-term": "yiannopoulos",
      "data-term-stats": [
        "1",
        "0.4",
        "0.000",
        "159",
        "w2v",
        "1"
      ]
    },
    "papiris": {
      "data-frequency": "78",
      "data-relevance": "128",
      "data-term": "papiris",
      "data-encoded-term": "papiris",
      "data-term-stats": [
        "1",
        "0.4",
        "0.000",
        "78",
        "w2v",
        "1"
      ]
    },
    "natik": {
      "data-frequency": "-1",
      "data-relevance": "127",
      "data-term": "natik",
      "data-encoded-term": "natik",
      "data-term-stats": [
        "1",
        "0.4",
        "0.000",
        "-1",
        "w2v",
        "1"
      ]
    },
    "pascu": {
      "data-frequency": "286",
      "data-relevance": "126",
      "data-term": "pascu",
      "data-encoded-term": "pascu",
      "data-term-stats": [
        "1",
        "0.4",
        "0.000",
        "286",
        "w2v",
        "1"
      ]
    },
    "aklilu": {
      "data-frequency": "113",
      "data-relevance": "125",
      "data-term": "aklilu",
      "data-encoded-term": "aklilu",
      "data-term-stats": [
        "1",
        "0.4",
        "0.000",
        "113",
        "w2v",
        "1"
      ]
    },
    "karttunen": {
      "data-frequency": "272",
      "data-relevance": "124",
      "data-term": "karttunen",
      "data-encoded-term": "karttunen",
      "data-term-stats": [
        "1",
        "0.4",
        "0.000",
        "272",
        "w2v",
        "1"
      ]
    },
    "platel": {
      "data-frequency": "114",
      "data-relevance": "123",
      "data-term": "platel",
      "data-encoded-term": "platel",
      "data-term-stats": [
        "1",
        "0.4",
        "0.000",
        "114",
        "w2v",
        "1"
      ]
    },
    "mastenbroek": {
      "data-frequency": "102",
      "data-relevance": "122",
      "data-term": "mastenbroek",
      "data-encoded-term": "mastenbroek",
      "data-term-stats": [
        "1",
        "0.4",
        "0.000",
        "102",
        "w2v",
        "1"
      ]
    },
    "skarphedinsson": {
      "data-frequency": "89",
      "data-relevance": "121",
      "data-term": "skarphedinsson",
      "data-encoded-term": "skarphedinsson",
      "data-term-stats": [
        "1",
        "0.4",
        "0.000",
        "89",
        "w2v",
        "1"
      ]
    },
    "ksenija": {
      "data-frequency": "622",
      "data-relevance": "120",
      "data-term": "ksenija",
      "data-encoded-term": "ksenija",
      "data-term-stats": [
        "1",
        "0.4",
        "0.000",
        "622",
        "w2v",
        "1"
      ]
    },
    "stanislovas": {
      "data-frequency": "328",
      "data-relevance": "119",
      "data-term": "stanislovas",
      "data-encoded-term": "stanislovas",
      "data-term-stats": [
        "1",
        "0.4",
        "0.000",
        "328",
        "w2v",
        "1"
      ]
    },
    "oliynyk": {
      "data-frequency": "283",
      "data-relevance": "118",
      "data-term": "oliynyk",
      "data-encoded-term": "oliynyk",
      "data-term-stats": [
        "1",
        "0.4",
        "0.000",
        "283",
        "w2v",
        "1"
      ]
    },
    "sozzini": {
      "data-frequency": "108",
      "data-relevance": "117",
      "data-term": "sozzini",
      "data-encoded-term": "sozzini",
      "data-term-stats": [
        "1",
        "0.4",
        "0.000",
        "108",
        "w2v",
        "1"
      ]
    },
    "isoflurane": {
      "data-frequency": "1696",
      "data-relevance": "116",
      "data-term": "isoflurane",
      "data-encoded-term": "isoflurane",
      "data-term-stats": [
        "1",
        "0.4",
        "0.000",
        "1696",
        "w2v",
        "1"
      ]
    },
    "panduru": {
      "data-frequency": "97",
      "data-relevance": "115",
      "data-term": "panduru",
      "data-encoded-term": "panduru",
      "data-term-stats": [
        "1",
        "0.4",
        "0.000",
        "97",
        "w2v",
        "1"
      ]
    },
    "1981-1990": {
      "data-frequency": "179456",
      "data-relevance": "114",
      "data-term": "1981-1990",
      "data-encoded-term": "1981-1990",
      "data-term-stats": [
        "1",
        "0.4",
        "0.000",
        "179456",
        "w2v",
        "1"
      ]
    },
    "bleedings": {
      "data-frequency": "14050",
      "data-relevance": "113",
      "data-term": "bleedings",
      "data-encoded-term": "bleedings",
      "data-term-stats": [
        "1",
        "0.4",
        "0.000",
        "14050",
        "w2v",
        "1"
      ]
    },
    "smas": {
      "data-frequency": "95",
      "data-relevance": "112",
      "data-term": "smas",
      "data-encoded-term": "smas",
      "data-term-stats": [
        "1",
        "0.4",
        "0.000",
        "95",
        "w2v",
        "1"
      ]
    },
    "1977-79": {
      "data-frequency": "49772",
      "data-relevance": "111",
      "data-term": "1977-79",
      "data-encoded-term": "1977-79",
      "data-term-stats": [
        "1",
        "0.4",
        "0.000",
        "49772",
        "w2v",
        "1"
      ]
    },
    "midorikawa": {
      "data-frequency": "445",
      "data-relevance": "110",
      "data-term": "midorikawa",
      "data-encoded-term": "midorikawa",
      "data-term-stats": [
        "1",
        "0.4",
        "0.000",
        "445",
        "w2v",
        "1"
      ]
    },
    "szemere": {
      "data-frequency": "167",
      "data-relevance": "109",
      "data-term": "szemere",
      "data-encoded-term": "szemere",
      "data-term-stats": [
        "1",
        "0.4",
        "0.000",
        "167",
        "w2v",
        "1"
      ]
    },
    "fecal incontinence": {
      "data-frequency": "155",
      "data-relevance": "108",
      "data-term": "fecal incontinence",
      "data-encoded-term": "fecal%20incontinence",
      "data-term-stats": [
        "1",
        "0.4",
        "0.000",
        "155",
        "wiki",
        "1"
      ]
    },
    "khamzat": {
      "data-frequency": "106",
      "data-relevance": "107",
      "data-term": "khamzat",
      "data-encoded-term": "khamzat",
      "data-term-stats": [
        "1",
        "0.4",
        "0.000",
        "106",
        "w2v",
        "1"
      ]
    },
    "lesion": {
      "data-frequency": "3780",
      "data-relevance": "106",
      "data-term": "lesion",
      "data-encoded-term": "lesion",
      "data-term-stats": [
        "1",
        "0.3",
        "0.000",
        "3780",
        "wiki",
        "1"
      ]
    },
    "urinary incontinence": {
      "data-frequency": "360",
      "data-relevance": "105",
      "data-term": "urinary incontinence",
      "data-encoded-term": "urinary%20incontinence",
      "data-term-stats": [
        "1",
        "0.3",
        "0.000",
        "360",
        "wiki",
        "1"
      ]
    },
    "paresis": {
      "data-frequency": "617",
      "data-relevance": "104",
      "data-term": "paresis",
      "data-encoded-term": "paresis",
      "data-term-stats": [
        "1",
        "0.2",
        "0.000",
        "617",
        "ol",
        "1"
      ]
    },
    "autonomic nervous system": {
      "data-frequency": "609",
      "data-relevance": "103",
      "data-term": "autonomic nervous system",
      "data-encoded-term": "autonomic%20nervous%20system",
      "data-term-stats": [
        "1",
        "0.3",
        "0.000",
        "609",
        "wiki",
        "1"
      ]
    },
    "scoliosis": {
      "data-frequency": "560",
      "data-relevance": "102",
      "data-term": "scoliosis",
      "data-encoded-term": "scoliosis",
      "data-term-stats": [
        "1",
        "0.2",
        "0.000",
        "560",
        "ol",
        "1"
      ]
    },
    "disability": {
      "data-frequency": "22896",
      "data-relevance": "101",
      "data-term": "disability",
      "data-encoded-term": "disability",
      "data-term-stats": [
        "1",
        "0.2",
        "0.000",
        "22896",
        "ol",
        "1"
      ]
    },
    "amputation": {
      "data-frequency": "2567",
      "data-relevance": "100",
      "data-term": "amputation",
      "data-encoded-term": "amputation",
      "data-term-stats": [
        "1",
        "0.2",
        "0.000",
        "2567",
        "ol",
        "1"
      ]
    },
    "aphasia": {
      "data-frequency": "902",
      "data-relevance": "99",
      "data-term": "aphasia",
      "data-encoded-term": "aphasia",
      "data-term-stats": [
        "1",
        "0.2",
        "0.000",
        "902",
        "ol",
        "1"
      ]
    },
    "dystrophy": {
      "data-frequency": "2154",
      "data-relevance": "98",
      "data-term": "dystrophy",
      "data-encoded-term": "dystrophy",
      "data-term-stats": [
        "1",
        "0.2",
        "0.000",
        "2154",
        "ol",
        "1"
      ]
    },
    "deformity": {
      "data-frequency": "1448",
      "data-relevance": "97",
      "data-term": "deformity",
      "data-encoded-term": "deformity",
      "data-term-stats": [
        "1",
        "0.2",
        "0.000",
        "1448",
        "ol",
        "1"
      ]
    },
    "neuritis": {
      "data-frequency": "502",
      "data-relevance": "96",
      "data-term": "neuritis",
      "data-encoded-term": "neuritis",
      "data-term-stats": [
        "1",
        "0.2",
        "0.000",
        "502",
        "ol",
        "1"
      ]
    },
    "epilepsy": {
      "data-frequency": "4397",
      "data-relevance": "95",
      "data-term": "epilepsy",
      "data-encoded-term": "epilepsy",
      "data-term-stats": [
        "1",
        "0.2",
        "0.000",
        "4397",
        "ol",
        "1"
      ]
    },
    "hydrocephalus": {
      "data-frequency": "600",
      "data-relevance": "94",
      "data-term": "hydrocephalus",
      "data-encoded-term": "hydrocephalus",
      "data-term-stats": [
        "1",
        "0.2",
        "0.000",
        "600",
        "ol",
        "1"
      ]
    },
    "deafness": {
      "data-frequency": "2606",
      "data-relevance": "93",
      "data-term": "deafness",
      "data-encoded-term": "deafness",
      "data-term-stats": [
        "1",
        "0.2",
        "0.000",
        "2606",
        "ol",
        "1"
      ]
    },
    "osteomyelitis": {
      "data-frequency": "577",
      "data-relevance": "92",
      "data-term": "osteomyelitis",
      "data-encoded-term": "osteomyelitis",
      "data-term-stats": [
        "1",
        "0.2",
        "0.000",
        "577",
        "ol",
        "1"
      ]
    },
    "hypoplasia": {
      "data-frequency": "787",
      "data-relevance": "91",
      "data-term": "hypoplasia",
      "data-encoded-term": "hypoplasia",
      "data-term-stats": [
        "1",
        "0.2",
        "0.000",
        "787",
        "ol",
        "1"
      ]
    },
    "nephritis": {
      "data-frequency": "600",
      "data-relevance": "90",
      "data-term": "nephritis",
      "data-encoded-term": "nephritis",
      "data-term-stats": [
        "1",
        "0.2",
        "0.000",
        "600",
        "ol",
        "1"
      ]
    },
    "arthritis": {
      "data-frequency": "5883",
      "data-relevance": "89",
      "data-term": "arthritis",
      "data-encoded-term": "arthritis",
      "data-term-stats": [
        "1",
        "0.2",
        "0.000",
        "5883",
        "ol",
        "1"
      ]
    },
    "autonomic dysreflexia": {
      "data-frequency": "-1",
      "data-relevance": "88",
      "data-term": "autonomic dysreflexia",
      "data-encoded-term": "autonomic%20dysreflexia",
      "data-term-stats": [
        "1",
        "0.2",
        "0.000",
        "-1",
        "wiki",
        "1"
      ]
    },
    "polio": {
      "data-frequency": "4118",
      "data-relevance": "87",
      "data-term": "polio",
      "data-encoded-term": "polio",
      "data-term-stats": [
        "1",
        "0.2",
        "0.000",
        "4118",
        "wiki",
        "1"
      ]
    },
    "myelopathy": {
      "data-frequency": "305",
      "data-relevance": "86",
      "data-term": "myelopathy",
      "data-encoded-term": "myelopathy",
      "data-term-stats": [
        "1",
        "0.1",
        "0.000",
        "305",
        "ol",
        "1"
      ]
    },
    "dysphasia": {
      "data-frequency": "50",
      "data-relevance": "85",
      "data-term": "dysphasia",
      "data-encoded-term": "dysphasia",
      "data-term-stats": [
        "1",
        "0.1",
        "0.000",
        "50",
        "ol",
        "1"
      ]
    },
    "syringomyelia": {
      "data-frequency": "95",
      "data-relevance": "84",
      "data-term": "syringomyelia",
      "data-encoded-term": "syringomyelia",
      "data-term-stats": [
        "1",
        "0.1",
        "0.000",
        "95",
        "ol",
        "1"
      ]
    },
    "spondylolisthesis": {
      "data-frequency": "60",
      "data-relevance": "83",
      "data-term": "spondylolisthesis",
      "data-encoded-term": "spondylolisthesis",
      "data-term-stats": [
        "1",
        "0.1",
        "0.000",
        "60",
        "ol",
        "1"
      ]
    },
    "torticollis": {
      "data-frequency": "103",
      "data-relevance": "82",
      "data-term": "torticollis",
      "data-encoded-term": "torticollis",
      "data-term-stats": [
        "1",
        "0.1",
        "0.000",
        "103",
        "ol",
        "1"
      ]
    },
    "myelomeningocele": {
      "data-frequency": "50",
      "data-relevance": "81",
      "data-term": "myelomeningocele",
      "data-encoded-term": "myelomeningocele",
      "data-term-stats": [
        "1",
        "0.1",
        "0.000",
        "50",
        "ol",
        "1"
      ]
    },
    "bulbar": {
      "data-frequency": "177",
      "data-relevance": "80",
      "data-term": "bulbar",
      "data-encoded-term": "bulbar",
      "data-term-stats": [
        "1",
        "0.1",
        "0.000",
        "177",
        "ol",
        "1"
      ]
    },
    "spondylitis": {
      "data-frequency": "332",
      "data-relevance": "79",
      "data-term": "spondylitis",
      "data-encoded-term": "spondylitis",
      "data-term-stats": [
        "1",
        "0.1",
        "0.000",
        "332",
        "ol",
        "1"
      ]
    },
    "myoclonus": {
      "data-frequency": "237",
      "data-relevance": "78",
      "data-term": "myoclonus",
      "data-encoded-term": "myoclonus",
      "data-term-stats": [
        "1",
        "0.1",
        "0.000",
        "237",
        "ol",
        "1"
      ]
    },
    "paresthesia": {
      "data-frequency": "217",
      "data-relevance": "77",
      "data-term": "paresthesia",
      "data-encoded-term": "paresthesia",
      "data-term-stats": [
        "1",
        "0.1",
        "0.000",
        "217",
        "ol",
        "1"
      ]
    },
    "kyphosis": {
      "data-frequency": "133",
      "data-relevance": "76",
      "data-term": "kyphosis",
      "data-encoded-term": "kyphosis",
      "data-term-stats": [
        "1",
        "0.1",
        "0.000",
        "133",
        "ol",
        "1"
      ]
    },
    "leukodystrophy": {
      "data-frequency": "146",
      "data-relevance": "75",
      "data-term": "leukodystrophy",
      "data-encoded-term": "leukodystrophy",
      "data-term-stats": [
        "1",
        "0.1",
        "0.000",
        "146",
        "ol",
        "1"
      ]
    },
    "neuropathies": {
      "data-frequency": "226",
      "data-relevance": "74",
      "data-term": "neuropathies",
      "data-encoded-term": "neuropathies",
      "data-term-stats": [
        "1",
        "0.1",
        "0.000",
        "226",
        "ol",
        "1"
      ]
    },
    "hypopituitarism": {
      "data-frequency": "262",
      "data-relevance": "73",
      "data-term": "hypopituitarism",
      "data-encoded-term": "hypopituitarism",
      "data-term-stats": [
        "1",
        "0.1",
        "0.000",
        "262",
        "ol",
        "1"
      ]
    },
    "arthrosis": {
      "data-frequency": "42",
      "data-relevance": "72",
      "data-term": "arthrosis",
      "data-encoded-term": "arthrosis",
      "data-term-stats": [
        "1",
        "0.1",
        "0.000",
        "42",
        "ol",
        "1"
      ]
    },
    "anosognosia": {
      "data-frequency": "52",
      "data-relevance": "71",
      "data-term": "anosognosia",
      "data-encoded-term": "anosognosia",
      "data-term-stats": [
        "1",
        "0.1",
        "0.000",
        "52",
        "ol",
        "1"
      ]
    },
    "arthropathy": {
      "data-frequency": "111",
      "data-relevance": "70",
      "data-term": "arthropathy",
      "data-encoded-term": "arthropathy",
      "data-term-stats": [
        "1",
        "0.1",
        "0.000",
        "111",
        "ol",
        "1"
      ]
    },
    "pyelonephritis": {
      "data-frequency": "132",
      "data-relevance": "69",
      "data-term": "pyelonephritis",
      "data-encoded-term": "pyelonephritis",
      "data-term-stats": [
        "1",
        "0.1",
        "0.000",
        "132",
        "ol",
        "1"
      ]
    },
    "ulcerations": {
      "data-frequency": "1770",
      "data-relevance": "68",
      "data-term": "ulcerations",
      "data-encoded-term": "ulcerations",
      "data-term-stats": [
        "1",
        "0.1",
        "0.000",
        "1770",
        "ol",
        "1"
      ]
    },
    "hypotonia": {
      "data-frequency": "392",
      "data-relevance": "67",
      "data-term": "hypotonia",
      "data-encoded-term": "hypotonia",
      "data-term-stats": [
        "1",
        "0.1",
        "0.000",
        "392",
        "ol",
        "1"
      ]
    },
    "laryngospasm": {
      "data-frequency": "276",
      "data-relevance": "66",
      "data-term": "laryngospasm",
      "data-encoded-term": "laryngospasm",
      "data-term-stats": [
        "1",
        "0.1",
        "0.000",
        "276",
        "ol",
        "1"
      ]
    },
    "thrombophlebitis": {
      "data-frequency": "272",
      "data-relevance": "65",
      "data-term": "thrombophlebitis",
      "data-encoded-term": "thrombophlebitis",
      "data-term-stats": [
        "1",
        "0.1",
        "0.000",
        "272",
        "ol",
        "1"
      ]
    },
    "clubfeet": {
      "data-frequency": "-1",
      "data-relevance": "64",
      "data-term": "clubfeet",
      "data-encoded-term": "clubfeet",
      "data-term-stats": [
        "1",
        "0.1",
        "0.000",
        "-1",
        "ol",
        "1"
      ]
    },
    "thyroiditis": {
      "data-frequency": "380",
      "data-relevance": "63",
      "data-term": "thyroiditis",
      "data-encoded-term": "thyroiditis",
      "data-term-stats": [
        "1",
        "0.1",
        "0.000",
        "380",
        "ol",
        "1"
      ]
    },
    "uremia": {
      "data-frequency": "215",
      "data-relevance": "62",
      "data-term": "uremia",
      "data-encoded-term": "uremia",
      "data-term-stats": [
        "1",
        "0.1",
        "0.000",
        "215",
        "ol",
        "1"
      ]
    },
    "vasovagal": {
      "data-frequency": "69",
      "data-relevance": "61",
      "data-term": "vasovagal",
      "data-encoded-term": "vasovagal",
      "data-term-stats": [
        "1",
        "0.1",
        "0.000",
        "69",
        "ol",
        "1"
      ]
    },
    "ambulation": {
      "data-frequency": "113",
      "data-relevance": "60",
      "data-term": "ambulation",
      "data-encoded-term": "ambulation",
      "data-term-stats": [
        "1",
        "0.1",
        "0.000",
        "113",
        "ol",
        "1"
      ]
    },
    "hydrocephaly": {
      "data-frequency": "44",
      "data-relevance": "59",
      "data-term": "hydrocephaly",
      "data-encoded-term": "hydrocephaly",
      "data-term-stats": [
        "1",
        "0.1",
        "0.000",
        "44",
        "ol",
        "1"
      ]
    },
    "cellulitis": {
      "data-frequency": "886",
      "data-relevance": "58",
      "data-term": "cellulitis",
      "data-encoded-term": "cellulitis",
      "data-term-stats": [
        "1",
        "0.1",
        "0.000",
        "886",
        "ol",
        "1"
      ]
    },
    "atresia": {
      "data-frequency": "517",
      "data-relevance": "57",
      "data-term": "atresia",
      "data-encoded-term": "atresia",
      "data-term-stats": [
        "1",
        "0.1",
        "0.000",
        "517",
        "ol",
        "1"
      ]
    },
    "bronchopneumonia": {
      "data-frequency": "209",
      "data-relevance": "56",
      "data-term": "bronchopneumonia",
      "data-encoded-term": "bronchopneumonia",
      "data-term-stats": [
        "1",
        "0.1",
        "0.000",
        "209",
        "ol",
        "1"
      ]
    },
    "claudication": {
      "data-frequency": "212",
      "data-relevance": "55",
      "data-term": "claudication",
      "data-encoded-term": "claudication",
      "data-term-stats": [
        "1",
        "0.1",
        "0.000",
        "212",
        "ol",
        "1"
      ]
    },
    "deep vein thrombosis": {
      "data-frequency": "510",
      "data-relevance": "54",
      "data-term": "deep vein thrombosis",
      "data-encoded-term": "deep%20vein%20thrombosis",
      "data-term-stats": [
        "1",
        "0.1",
        "0.000",
        "510",
        "wiki",
        "1"
      ]
    },
    "meningoencephalitis": {
      "data-frequency": "199",
      "data-relevance": "53",
      "data-term": "meningoencephalitis",
      "data-encoded-term": "meningoencephalitis",
      "data-term-stats": [
        "1",
        "0.1",
        "0.000",
        "199",
        "ol",
        "1"
      ]
    },
    "traffic collision": {
      "data-frequency": "648",
      "data-relevance": "52",
      "data-term": "traffic collision",
      "data-encoded-term": "traffic%20collision",
      "data-term-stats": [
        "1",
        "0.0",
        "0.000",
        "648",
        "wiki",
        "1"
      ]
    },
    "spinal cord": {
      "data-frequency": "4805",
      "data-relevance": "51",
      "data-term": "spinal cord",
      "data-encoded-term": "spinal%20cord",
      "data-term-stats": [
        "1",
        "0.1",
        "0.000",
        "4805",
        "wiki",
        "1"
      ]
    },
    "transverse myelitis": {
      "data-frequency": "96",
      "data-relevance": "50",
      "data-term": "transverse myelitis",
      "data-encoded-term": "transverse%20myelitis",
      "data-term-stats": [
        "1",
        "-0.0",
        "0.000",
        "96",
        "wiki",
        "1"
      ]
    },
    "latin": {
      "data-frequency": "197809",
      "data-relevance": "49",
      "data-term": "latin",
      "data-encoded-term": "latin",
      "data-term-stats": [
        "1",
        "0.0",
        "0.000",
        "197809",
        "wiki",
        "1"
      ]
    },
    "degenerative disorder": {
      "data-frequency": "52",
      "data-relevance": "48",
      "data-term": "degenerative disorder",
      "data-encoded-term": "degenerative%20disorder",
      "data-term-stats": [
        "1",
        "-0.1",
        "0.000",
        "52",
        "ol",
        "1"
      ]
    },
    "guillain–barré syndrome": {
      "data-frequency": "614",
      "data-relevance": "47",
      "data-term": "guillain–barré syndrome",
      "data-encoded-term": "guillain%E2%80%93barr%C3%A9%20syndrome",
      "data-term-stats": [
        "1",
        "-0.1",
        "0.000",
        "614",
        "wiki",
        "1"
      ]
    },
    "spinal curvature": {
      "data-frequency": "52",
      "data-relevance": "46",
      "data-term": "spinal curvature",
      "data-encoded-term": "spinal%20curvature",
      "data-term-stats": [
        "1",
        "-0.1",
        "0.000",
        "52",
        "ol",
        "1"
      ]
    },
    "osteogenesis imperfecta": {
      "data-frequency": "186",
      "data-relevance": "45",
      "data-term": "osteogenesis imperfecta",
      "data-encoded-term": "osteogenesis%20imperfecta",
      "data-term-stats": [
        "1",
        "-0.1",
        "0.000",
        "186",
        "ol",
        "1"
      ]
    },
    "spina bifida": {
      "data-frequency": "527",
      "data-relevance": "44",
      "data-term": "spina bifida",
      "data-encoded-term": "spina%20bifida",
      "data-term-stats": [
        "1",
        "-0.1",
        "0.000",
        "527",
        "ol",
        "1"
      ]
    },
    "visual impairment": {
      "data-frequency": "1139",
      "data-relevance": "43",
      "data-term": "visual impairment",
      "data-encoded-term": "visual%20impairment",
      "data-term-stats": [
        "1",
        "-0.1",
        "0.000",
        "1139",
        "ol",
        "1"
      ]
    },
    "trigeminal neuralgia": {
      "data-frequency": "140",
      "data-relevance": "42",
      "data-term": "trigeminal neuralgia",
      "data-encoded-term": "trigeminal%20neuralgia",
      "data-term-stats": [
        "1",
        "-0.1",
        "0.000",
        "140",
        "ol",
        "1"
      ]
    },
    "retrograde amnesia": {
      "data-frequency": "155",
      "data-relevance": "41",
      "data-term": "retrograde amnesia",
      "data-encoded-term": "retrograde%20amnesia",
      "data-term-stats": [
        "1",
        "-0.1",
        "0.000",
        "155",
        "ol",
        "1"
      ]
    },
    "cerebrovascular accident": {
      "data-frequency": "175",
      "data-relevance": "40",
      "data-term": "cerebrovascular accident",
      "data-encoded-term": "cerebrovascular%20accident",
      "data-term-stats": [
        "1",
        "-0.1",
        "0.000",
        "175",
        "ol",
        "1"
      ]
    },
    "phantom limb syndrome": {
      "data-frequency": "-1",
      "data-relevance": "39",
      "data-term": "phantom limb syndrome",
      "data-encoded-term": "phantom%20limb%20syndrome",
      "data-term-stats": [
        "1",
        "-0.1",
        "0.000",
        "-1",
        "ol",
        "1"
      ]
    },
    "essential tremor": {
      "data-frequency": "112",
      "data-relevance": "38",
      "data-term": "essential tremor",
      "data-encoded-term": "essential%20tremor",
      "data-term-stats": [
        "1",
        "-0.1",
        "0.000",
        "112",
        "ol",
        "1"
      ]
    },
    "neurogenic bladder": {
      "data-frequency": "51",
      "data-relevance": "37",
      "data-term": "neurogenic bladder",
      "data-encoded-term": "neurogenic%20bladder",
      "data-term-stats": [
        "1",
        "-0.1",
        "0.000",
        "51",
        "ol",
        "1"
      ]
    },
    "cerebral thrombosis": {
      "data-frequency": "116",
      "data-relevance": "36",
      "data-term": "cerebral thrombosis",
      "data-encoded-term": "cerebral%20thrombosis",
      "data-term-stats": [
        "1",
        "-0.1",
        "0.000",
        "116",
        "ol",
        "1"
      ]
    },
    "congenital abnormality": {
      "data-frequency": "78",
      "data-relevance": "35",
      "data-term": "congenital abnormality",
      "data-encoded-term": "congenital%20abnormality",
      "data-term-stats": [
        "1",
        "-0.1",
        "0.000",
        "78",
        "ol",
        "1"
      ]
    },
    "generalized epilepsy": {
      "data-frequency": "48",
      "data-relevance": "34",
      "data-term": "generalized epilepsy",
      "data-encoded-term": "generalized%20epilepsy",
      "data-term-stats": [
        "1",
        "-0.1",
        "0.000",
        "48",
        "ol",
        "1"
      ]
    },
    "nerve entrapment": {
      "data-frequency": "88",
      "data-relevance": "33",
      "data-term": "nerve entrapment",
      "data-encoded-term": "nerve%20entrapment",
      "data-term-stats": [
        "1",
        "-0.1",
        "0.000",
        "88",
        "ol",
        "1"
      ]
    },
    "spastic paralysis": {
      "data-frequency": "51",
      "data-relevance": "32",
      "data-term": "spastic paralysis",
      "data-encoded-term": "spastic%20paralysis",
      "data-term-stats": [
        "1",
        "-0.1",
        "0.000",
        "51",
        "ol",
        "1"
      ]
    },
    "intermittent claudication": {
      "data-frequency": "173",
      "data-relevance": "31",
      "data-term": "intermittent claudication",
      "data-encoded-term": "intermittent%20claudication",
      "data-term-stats": [
        "1",
        "-0.1",
        "0.000",
        "173",
        "ol",
        "1"
      ]
    },
    "rheumatic disease": {
      "data-frequency": "81",
      "data-relevance": "30",
      "data-term": "rheumatic disease",
      "data-encoded-term": "rheumatic%20disease",
      "data-term-stats": [
        "1",
        "-0.1",
        "0.000",
        "81",
        "ol",
        "1"
      ]
    },
    "juvenile rheumatoid arthritis": {
      "data-frequency": "177",
      "data-relevance": "29",
      "data-term": "juvenile rheumatoid arthritis",
      "data-encoded-term": "juvenile%20rheumatoid%20arthritis",
      "data-term-stats": [
        "1",
        "-0.1",
        "0.000",
        "177",
        "ol",
        "1"
      ]
    },
    "herpes encephalitis": {
      "data-frequency": "317",
      "data-relevance": "28",
      "data-term": "herpes encephalitis",
      "data-encoded-term": "herpes%20encephalitis",
      "data-term-stats": [
        "1",
        "-0.1",
        "0.000",
        "317",
        "ol",
        "1"
      ]
    },
    "degenerative arthritis": {
      "data-frequency": "45",
      "data-relevance": "27",
      "data-term": "degenerative arthritis",
      "data-encoded-term": "degenerative%20arthritis",
      "data-term-stats": [
        "1",
        "-0.1",
        "0.000",
        "45",
        "ol",
        "1"
      ]
    },
    "diaphragmatic hernia": {
      "data-frequency": "104",
      "data-relevance": "26",
      "data-term": "diaphragmatic hernia",
      "data-encoded-term": "diaphragmatic%20hernia",
      "data-term-stats": [
        "1",
        "-0.1",
        "0.000",
        "104",
        "ol",
        "1"
      ]
    },
    "cardiac tamponade": {
      "data-frequency": "247",
      "data-relevance": "25",
      "data-term": "cardiac tamponade",
      "data-encoded-term": "cardiac%20tamponade",
      "data-term-stats": [
        "1",
        "-0.1",
        "0.000",
        "247",
        "ol",
        "1"
      ]
    },
    "lymphocytic leukemia": {
      "data-frequency": "437",
      "data-relevance": "24",
      "data-term": "lymphocytic leukemia",
      "data-encoded-term": "lymphocytic%20leukemia",
      "data-term-stats": [
        "1",
        "-0.1",
        "0.000",
        "437",
        "ol",
        "1"
      ]
    },
    "aplastic anaemia": {
      "data-frequency": "58",
      "data-relevance": "23",
      "data-term": "aplastic anaemia",
      "data-encoded-term": "aplastic%20anaemia",
      "data-term-stats": [
        "1",
        "-0.1",
        "0.000",
        "58",
        "ol",
        "1"
      ]
    },
    "embryonal rhabdomyosarcoma": {
      "data-frequency": "-1",
      "data-relevance": "22",
      "data-term": "embryonal rhabdomyosarcoma",
      "data-encoded-term": "embryonal%20rhabdomyosarcoma",
      "data-term-stats": [
        "1",
        "-0.1",
        "0.000",
        "-1",
        "ol",
        "1"
      ]
    },
    "lupus erythematosus": {
      "data-frequency": "1054",
      "data-relevance": "21",
      "data-term": "lupus erythematosus",
      "data-encoded-term": "lupus%20erythematosus",
      "data-term-stats": [
        "1",
        "-0.1",
        "0.000",
        "1054",
        "ol",
        "1"
      ]
    },
    "myotonic dystrophy": {
      "data-frequency": "130",
      "data-relevance": "20",
      "data-term": "myotonic dystrophy",
      "data-encoded-term": "myotonic%20dystrophy",
      "data-term-stats": [
        "1",
        "-0.1",
        "0.000",
        "130",
        "ol",
        "1"
      ]
    },
    "cardiogenic shock": {
      "data-frequency": "118",
      "data-relevance": "19",
      "data-term": "cardiogenic shock",
      "data-encoded-term": "cardiogenic%20shock",
      "data-term-stats": [
        "1",
        "-0.1",
        "0.000",
        "118",
        "ol",
        "1"
      ]
    },
    "becker muscular dystrophy": {
      "data-frequency": "94",
      "data-relevance": "18",
      "data-term": "becker muscular dystrophy",
      "data-encoded-term": "becker%20muscular%20dystrophy",
      "data-term-stats": [
        "1",
        "-0.1",
        "0.000",
        "94",
        "ol",
        "1"
      ]
    },
    "expressive aphasia": {
      "data-frequency": "50",
      "data-relevance": "17",
      "data-term": "expressive aphasia",
      "data-encoded-term": "expressive%20aphasia",
      "data-term-stats": [
        "1",
        "-0.1",
        "0.000",
        "50",
        "ol",
        "1"
      ]
    },
    "congenital anomaly": {
      "data-frequency": "79",
      "data-relevance": "16",
      "data-term": "congenital anomaly",
      "data-encoded-term": "congenital%20anomaly",
      "data-term-stats": [
        "1",
        "-0.1",
        "0.000",
        "79",
        "ol",
        "1"
      ]
    },
    "imperforate anus": {
      "data-frequency": "52",
      "data-relevance": "15",
      "data-term": "imperforate anus",
      "data-encoded-term": "imperforate%20anus",
      "data-term-stats": [
        "1",
        "-0.1",
        "0.000",
        "52",
        "ol",
        "1"
      ]
    },
    "hypovolemic shock": {
      "data-frequency": "104",
      "data-relevance": "14",
      "data-term": "hypovolemic shock",
      "data-encoded-term": "hypovolemic%20shock",
      "data-term-stats": [
        "1",
        "-0.1",
        "0.000",
        "104",
        "ol",
        "1"
      ]
    },
    "phantom limb pain": {
      "data-frequency": "49",
      "data-relevance": "13",
      "data-term": "phantom limb pain",
      "data-encoded-term": "phantom%20limb%20pain",
      "data-term-stats": [
        "1",
        "-0.1",
        "0.000",
        "49",
        "ol",
        "1"
      ]
    },
    "retinitis pigmentosa": {
      "data-frequency": "588",
      "data-relevance": "12",
      "data-term": "retinitis pigmentosa",
      "data-encoded-term": "retinitis%20pigmentosa",
      "data-term-stats": [
        "1",
        "-0.1",
        "0.000",
        "588",
        "ol",
        "1"
      ]
    },
    "pulmonary stenosis": {
      "data-frequency": "225",
      "data-relevance": "11",
      "data-term": "pulmonary stenosis",
      "data-encoded-term": "pulmonary%20stenosis",
      "data-term-stats": [
        "1",
        "-0.1",
        "0.000",
        "225",
        "ol",
        "1"
      ]
    },
    "amyotrophic lateral sclerosis": {
      "data-frequency": "1089",
      "data-relevance": "10",
      "data-term": "amyotrophic lateral sclerosis",
      "data-encoded-term": "amyotrophic%20lateral%20sclerosis",
      "data-term-stats": [
        "1",
        "-0.1",
        "0.000",
        "1089",
        "ol",
        "1"
      ]
    },
    "lymphoblastic leukemia": {
      "data-frequency": "410",
      "data-relevance": "9",
      "data-term": "lymphoblastic leukemia",
      "data-encoded-term": "lymphoblastic%20leukemia",
      "data-term-stats": [
        "1",
        "-0.1",
        "0.000",
        "410",
        "ol",
        "1"
      ]
    },
    "spinal cord injuries": {
      "data-frequency": "2164",
      "data-relevance": "8",
      "data-term": "spinal cord injuries",
      "data-encoded-term": "spinal%20cord%20injuries",
      "data-term-stats": [
        "1",
        "-0.2",
        "0.000",
        "2164",
        "wiki",
        "1"
      ]
    },
    "intervertebral disc": {
      "data-frequency": "205",
      "data-relevance": "7",
      "data-term": "intervertebral disc",
      "data-encoded-term": "intervertebral%20disc",
      "data-term-stats": [
        "1",
        "-0.2",
        "0.000",
        "205",
        "wiki",
        "1"
      ]
    },
    "hand strength": {
      "data-frequency": "36146",
      "data-relevance": "6",
      "data-term": "hand strength",
      "data-encoded-term": "hand%20strength",
      "data-term-stats": [
        "1",
        "-0.3",
        "0.000",
        "36146",
        "wiki",
        "1"
      ]
    },
    "american spinal injury association": {
      "data-frequency": "1033",
      "data-relevance": "5",
      "data-term": "american spinal injury association",
      "data-encoded-term": "american%20spinal%20injury%20association",
      "data-term-stats": [
        "1",
        "-0.3",
        "0.000",
        "1033",
        "wiki",
        "1"
      ]
    },
    "activities of daily living": {
      "data-frequency": "319",
      "data-relevance": "4",
      "data-term": "activities of daily living",
      "data-encoded-term": "activities%20of%20daily%20living",
      "data-term-stats": [
        "1",
        "-0.3",
        "0.000",
        "319",
        "wiki",
        "1"
      ]
    },
    "botulinum toxin": {
      "data-frequency": "589",
      "data-relevance": "3",
      "data-term": "botulinum toxin",
      "data-encoded-term": "botulinum%20toxin",
      "data-term-stats": [
        "1",
        "-0.3",
        "0.000",
        "589",
        "wiki",
        "1"
      ]
    },
    "christopher reeve": {
      "data-frequency": "706",
      "data-relevance": "2",
      "data-term": "christopher reeve",
      "data-encoded-term": "christopher%20reeve",
      "data-term-stats": [
        "1",
        "-0.3",
        "0.000",
        "706",
        "wiki",
        "1"
      ]
    },
    "synaptic plasticity": {
      "data-frequency": "727",
      "data-relevance": "1",
      "data-term": "synaptic plasticity",
      "data-encoded-term": "synaptic%20plasticity",
      "data-term-stats": [
        "1",
        "-0.3",
        "0.000",
        "727",
        "wiki",
        "1"
      ]
    },
    "greek language": {
      "data-frequency": "35566",
      "data-relevance": "0",
      "data-term": "greek language",
      "data-encoded-term": "greek%20language",
      "data-term-stats": [
        "1",
        "-0.3",
        "0.000",
        "35566",
        "wiki",
        "1"
      ]
    }
  },
  "related_ngsl": {},
  "related_awl_economics": {},
  "related_awl_computer_science_s": {},
  "related_awl_computer_science": {},
  "irregular_words": {},
  "plurals": {},
  "gerunds": {},
  "wooordhunt": {
    "similar_words": [],
    "word_forms": [],
    "examples": []
  },
  "custom_words": [],
  "important_word": {
    "word_forms": [
      "quadriplegias"
    ],
    "synonyms": [
      "tetraplegia"
    ],
    "antonyms": [],
    "similar_terms": [],
    "gerunds": [],
    "irregular_words": [],
    "relatedwords": [
      "spastic",
      "palsy",
      "neck",
      "paraplegia",
      "tetraplegia",
      "limb",
      "empyema",
      "hemiplegia",
      "dysgraphia",
      "torso",
      "quadriplegias",
      "achondroplasia",
      "quadriplegic",
      "paralysis"
    ]
  }
}