{
  "conceptnet": {
    "related_terms": {
      "filtered": {
        "@id": "/a/[/r/RelatedTo/,/c/en/unfiltered/a/,/c/en/filtered/]",
        "weight": 1.0,
        "start": {
          "@id": "/c/en/unfiltered/a",
          "@type": "Node",
          "label": "unfiltered",
          "language": "en",
          "sense_label": "a",
          "term": "/c/en/unfiltered"
        },
        "end": {
          "@id": "/c/en/filtered",
          "@type": "Node",
          "label": "filtered",
          "language": "en",
          "term": "/c/en/filtered"
        }
      },
      "filter": {
        "@id": "/a/[/r/RelatedTo/,/c/en/unfiltered/a/,/c/en/filter/]",
        "weight": 1.0,
        "start": {
          "@id": "/c/en/unfiltered/a",
          "@type": "Node",
          "label": "unfiltered",
          "language": "en",
          "sense_label": "a",
          "term": "/c/en/unfiltered"
        },
        "end": {
          "@id": "/c/en/filter",
          "@type": "Node",
          "label": "filter",
          "language": "en",
          "term": "/c/en/filter"
        }
      },
      "woodbine": {
        "@id": "/a/[/r/RelatedTo/,/c/en/woodbine/n/,/c/en/unfiltered/]",
        "weight": 1.0,
        "start": {
          "@id": "/c/en/woodbine/n",
          "@type": "Node",
          "label": "woodbine",
          "language": "en",
          "sense_label": "n",
          "term": "/c/en/woodbine"
        },
        "end": {
          "@id": "/c/en/unfiltered",
          "@type": "Node",
          "label": "unfiltered",
          "language": "en",
          "term": "/c/en/unfiltered"
        }
      }
    },
    "distinct_terms": {},
    "synonyms": {},
    "antonyms": {
      "filtered": {
        "@id": "/a/[/r/Antonym/,/c/en/unfiltered/a/,/c/en/filtered/]",
        "weight": 1.0,
        "start": {
          "@id": "/c/en/unfiltered/a",
          "@type": "Node",
          "label": "unfiltered",
          "language": "en",
          "sense_label": "a",
          "term": "/c/en/unfiltered"
        },
        "end": {
          "@id": "/c/en/filtered",
          "@type": "Node",
          "label": "filtered",
          "language": "en",
          "term": "/c/en/filtered"
        }
      }
    },
    "similar_terms": {},
    "word_forms": {
      "uninfiltrated": {
        "@id": "/a/[/r/FormOf/,/c/en/uninfiltrated/a/,/c/en/unfiltered/]",
        "weight": 1.0,
        "start": {
          "@id": "/c/en/uninfiltrated/a",
          "@type": "Node",
          "label": "uninfiltrated",
          "language": "en",
          "sense_label": "a",
          "term": "/c/en/uninfiltrated"
        },
        "end": {
          "@id": "/c/en/unfiltered",
          "@type": "Node",
          "label": "unfiltered",
          "language": "en",
          "term": "/c/en/unfiltered"
        }
      }
    }
  },
  "relatedwords": {
    "unedited": {
      "data-frequency": "1946",
      "data-relevance": "129",
      "data-term": "unedited",
      "data-encoded-term": "unedited",
      "data-term-stats": [
        "1",
        "0.9",
        "0.000",
        "1946",
        "ol,reddit-slashes",
        "1"
      ]
    },
    "uncut": {
      "data-frequency": "7085",
      "data-relevance": "128",
      "data-term": "uncut",
      "data-encoded-term": "uncut",
      "data-term-stats": [
        "1",
        "0.9",
        "0.000",
        "7085",
        "ol,reddit-slashes",
        "1"
      ]
    },
    "raw": {
      "data-frequency": "42007",
      "data-relevance": "127",
      "data-term": "raw",
      "data-encoded-term": "raw",
      "data-term-stats": [
        "1",
        "0.9",
        "0.000",
        "42007",
        "ol,reddit-slashes",
        "1"
      ]
    },
    "uncensored": {
      "data-frequency": "4030",
      "data-relevance": "126",
      "data-term": "uncensored",
      "data-encoded-term": "uncensored",
      "data-term-stats": [
        "1",
        "1.8",
        "0.000",
        "4030",
        "ol,reddit-slashes|reverse-net",
        "1"
      ]
    },
    "filtered": {
      "data-frequency": "4824",
      "data-relevance": "125",
      "data-term": "filtered",
      "data-encoded-term": "filtered",
      "data-term-stats": [
        "1",
        "1.1",
        "0.000",
        "4824",
        "ol,reddit-slashes",
        "1"
      ]
    },
    "untainted": {
      "data-frequency": "385",
      "data-relevance": "124",
      "data-term": "untainted",
      "data-encoded-term": "untainted",
      "data-term-stats": [
        "1",
        "0.9",
        "0.000",
        "385",
        "ol,reddit-slashes",
        "1"
      ]
    },
    "direct": {
      "data-frequency": "218794",
      "data-relevance": "123",
      "data-term": "direct",
      "data-encoded-term": "direct",
      "data-term-stats": [
        "1",
        "0.9",
        "0.000",
        "218794",
        "ol,reddit-slashes",
        "1"
      ]
    },
    "air america radio": {
      "data-frequency": "60022",
      "data-relevance": "122",
      "data-term": "air america radio",
      "data-encoded-term": "air%20america%20radio",
      "data-term-stats": [
        "1",
        "0.5",
        "0.000",
        "60022",
        "wiki",
        "1"
      ]
    },
    "rachel maddow": {
      "data-frequency": "654",
      "data-relevance": "121",
      "data-term": "rachel maddow",
      "data-encoded-term": "rachel%20maddow",
      "data-term-stats": [
        "1",
        "0.4",
        "0.000",
        "654",
        "wiki",
        "1"
      ]
    },
    "unvarnished": {
      "data-frequency": "324",
      "data-relevance": "120",
      "data-term": "unvarnished",
      "data-encoded-term": "unvarnished",
      "data-term-stats": [
        "1",
        "0.2",
        "0.000",
        "324",
        "ol",
        "1"
      ]
    },
    "undiluted": {
      "data-frequency": "336",
      "data-relevance": "119",
      "data-term": "undiluted",
      "data-encoded-term": "undiluted",
      "data-term-stats": [
        "1",
        "0.2",
        "0.000",
        "336",
        "ol",
        "1"
      ]
    },
    "unadulterated": {
      "data-frequency": "584",
      "data-relevance": "118",
      "data-term": "unadulterated",
      "data-encoded-term": "unadulterated",
      "data-term-stats": [
        "1",
        "0.2",
        "0.000",
        "584",
        "ol",
        "1"
      ]
    },
    "distilled": {
      "data-frequency": "3993",
      "data-relevance": "117",
      "data-term": "distilled",
      "data-encoded-term": "distilled",
      "data-term-stats": [
        "1",
        "0.2",
        "0.000",
        "3993",
        "ol",
        "1"
      ]
    },
    "unbiased": {
      "data-frequency": "2554",
      "data-relevance": "116",
      "data-term": "unbiased",
      "data-encoded-term": "unbiased",
      "data-term-stats": [
        "1",
        "0.2",
        "0.000",
        "2554",
        "ol",
        "1"
      ]
    },
    "drinkable": {
      "data-frequency": "598",
      "data-relevance": "115",
      "data-term": "drinkable",
      "data-encoded-term": "drinkable",
      "data-term-stats": [
        "1",
        "0.2",
        "0.000",
        "598",
        "ol",
        "1"
      ]
    },
    "unscripted": {
      "data-frequency": "1395",
      "data-relevance": "114",
      "data-term": "unscripted",
      "data-encoded-term": "unscripted",
      "data-term-stats": [
        "1",
        "0.2",
        "0.000",
        "1395",
        "ol",
        "1"
      ]
    },
    "unfettered": {
      "data-frequency": "1333",
      "data-relevance": "113",
      "data-term": "unfettered",
      "data-encoded-term": "unfettered",
      "data-term-stats": [
        "1",
        "0.2",
        "0.000",
        "1333",
        "ol",
        "1"
      ]
    },
    "uninhibited": {
      "data-frequency": "937",
      "data-relevance": "112",
      "data-term": "uninhibited",
      "data-encoded-term": "uninhibited",
      "data-term-stats": [
        "1",
        "0.2",
        "0.000",
        "937",
        "ol",
        "1"
      ]
    },
    "candid": {
      "data-frequency": "5518",
      "data-relevance": "111",
      "data-term": "candid",
      "data-encoded-term": "candid",
      "data-term-stats": [
        "1",
        "0.2",
        "0.000",
        "5518",
        "ol",
        "1"
      ]
    },
    "truthful": {
      "data-frequency": "2674",
      "data-relevance": "110",
      "data-term": "truthful",
      "data-encoded-term": "truthful",
      "data-term-stats": [
        "1",
        "0.2",
        "0.000",
        "2674",
        "ol",
        "1"
      ]
    },
    "censored": {
      "data-frequency": "6554",
      "data-relevance": "109",
      "data-term": "censored",
      "data-encoded-term": "censored",
      "data-term-stats": [
        "1",
        "0.2",
        "0.000",
        "6554",
        "ol",
        "1"
      ]
    },
    "refreshing": {
      "data-frequency": "4228",
      "data-relevance": "108",
      "data-term": "refreshing",
      "data-encoded-term": "refreshing",
      "data-term-stats": [
        "1",
        "0.2",
        "0.000",
        "4228",
        "ol",
        "1"
      ]
    },
    "unimpeded": {
      "data-frequency": "791",
      "data-relevance": "107",
      "data-term": "unimpeded",
      "data-encoded-term": "unimpeded",
      "data-term-stats": [
        "1",
        "0.2",
        "0.000",
        "791",
        "ol",
        "1"
      ]
    },
    "instantaneous": {
      "data-frequency": "2850",
      "data-relevance": "106",
      "data-term": "instantaneous",
      "data-encoded-term": "instantaneous",
      "data-term-stats": [
        "1",
        "0.2",
        "0.000",
        "2850",
        "ol",
        "1"
      ]
    },
    "bottled": {
      "data-frequency": "4385",
      "data-relevance": "105",
      "data-term": "bottled",
      "data-encoded-term": "bottled",
      "data-term-stats": [
        "1",
        "0.2",
        "0.000",
        "4385",
        "ol",
        "1"
      ]
    },
    "uncorrupted": {
      "data-frequency": "250",
      "data-relevance": "104",
      "data-term": "uncorrupted",
      "data-encoded-term": "uncorrupted",
      "data-term-stats": [
        "1",
        "0.2",
        "0.000",
        "250",
        "ol",
        "1"
      ]
    },
    "opinionated": {
      "data-frequency": "1156",
      "data-relevance": "103",
      "data-term": "opinionated",
      "data-encoded-term": "opinionated",
      "data-term-stats": [
        "1",
        "0.2",
        "0.000",
        "1156",
        "ol",
        "1"
      ]
    },
    "omniscient": {
      "data-frequency": "1078",
      "data-relevance": "102",
      "data-term": "omniscient",
      "data-encoded-term": "omniscient",
      "data-term-stats": [
        "1",
        "0.2",
        "0.000",
        "1078",
        "ol",
        "1"
      ]
    },
    "purest": {
      "data-frequency": "1943",
      "data-relevance": "101",
      "data-term": "purest",
      "data-encoded-term": "purest",
      "data-term-stats": [
        "1",
        "0.2",
        "0.000",
        "1943",
        "ol",
        "1"
      ]
    },
    "conversational": {
      "data-frequency": "2370",
      "data-relevance": "100",
      "data-term": "conversational",
      "data-encoded-term": "conversational",
      "data-term-stats": [
        "1",
        "0.2",
        "0.000",
        "2370",
        "ol",
        "1"
      ]
    },
    "untreated": {
      "data-frequency": "3216",
      "data-relevance": "99",
      "data-term": "untreated",
      "data-encoded-term": "untreated",
      "data-term-stats": [
        "1",
        "0.0",
        "0.000",
        "3216",
        "reddit-slashes",
        "1"
      ]
    },
    "anonymous": {
      "data-frequency": "32276",
      "data-relevance": "98",
      "data-term": "anonymous",
      "data-encoded-term": "anonymous",
      "data-term-stats": [
        "1",
        "0.2",
        "0.000",
        "32276",
        "ol",
        "1"
      ]
    },
    "untrammeled": {
      "data-frequency": "131",
      "data-relevance": "97",
      "data-term": "untrammeled",
      "data-encoded-term": "untrammeled",
      "data-term-stats": [
        "1",
        "0.2",
        "0.000",
        "131",
        "ol",
        "1"
      ]
    },
    "nuanced": {
      "data-frequency": "2649",
      "data-relevance": "96",
      "data-term": "nuanced",
      "data-encoded-term": "nuanced",
      "data-term-stats": [
        "1",
        "0.2",
        "0.000",
        "2649",
        "ol",
        "1"
      ]
    },
    "honest": {
      "data-frequency": "22205",
      "data-relevance": "95",
      "data-term": "honest",
      "data-encoded-term": "honest",
      "data-term-stats": [
        "1",
        "0.2",
        "0.000",
        "22205",
        "ol",
        "1"
      ]
    },
    "insightful": {
      "data-frequency": "2500",
      "data-relevance": "94",
      "data-term": "insightful",
      "data-encoded-term": "insightful",
      "data-term-stats": [
        "1",
        "0.2",
        "0.000",
        "2500",
        "ol",
        "1"
      ]
    },
    "unconstrained": {
      "data-frequency": "619",
      "data-relevance": "93",
      "data-term": "unconstrained",
      "data-encoded-term": "unconstrained",
      "data-term-stats": [
        "1",
        "0.2",
        "0.000",
        "619",
        "ol",
        "1"
      ]
    },
    "open": {
      "data-frequency": "550083",
      "data-relevance": "92",
      "data-term": "open",
      "data-encoded-term": "open",
      "data-term-stats": [
        "1",
        "0.0",
        "0.000",
        "550083",
        "reddit-slashes",
        "1"
      ]
    },
    "edited": {
      "data-frequency": "222029",
      "data-relevance": "91",
      "data-term": "edited",
      "data-encoded-term": "edited",
      "data-term-stats": [
        "undefined",
        "0.0",
        "0.000",
        "222029",
        "undefined",
        "undefined"
      ]
    },
    "unadorned": {
      "data-frequency": "1352",
      "data-relevance": "90",
      "data-term": "unadorned",
      "data-encoded-term": "unadorned",
      "data-term-stats": [
        "1",
        "0.2",
        "0.000",
        "1352",
        "ol",
        "1"
      ]
    },
    "unclouded": {
      "data-frequency": "102",
      "data-relevance": "89",
      "data-term": "unclouded",
      "data-encoded-term": "unclouded",
      "data-term-stats": [
        "1",
        "0.2",
        "0.000",
        "102",
        "ol",
        "1"
      ]
    },
    "unpasteurized": {
      "data-frequency": "252",
      "data-relevance": "88",
      "data-term": "unpasteurized",
      "data-encoded-term": "unpasteurized",
      "data-term-stats": [
        "1",
        "0.1",
        "0.000",
        "252",
        "ol",
        "1"
      ]
    },
    "unheated": {
      "data-frequency": "481",
      "data-relevance": "87",
      "data-term": "unheated",
      "data-encoded-term": "unheated",
      "data-term-stats": [
        "1",
        "0.0",
        "0.000",
        "481",
        "reddit-slashes",
        "1"
      ]
    },
    "unfined": {
      "data-frequency": "-1",
      "data-relevance": "86",
      "data-term": "unfined",
      "data-encoded-term": "unfined",
      "data-term-stats": [
        "1",
        "-0.1",
        "0.000",
        "-1",
        "reddit-slashes",
        "1"
      ]
    },
    "hazy": {
      "data-frequency": "2253",
      "data-relevance": "85",
      "data-term": "hazy",
      "data-encoded-term": "hazy",
      "data-term-stats": [
        "undefined",
        "0.0",
        "0.000",
        "2253",
        "undefined",
        "undefined"
      ]
    },
    "fermented": {
      "data-frequency": "5240",
      "data-relevance": "84",
      "data-term": "fermented",
      "data-encoded-term": "fermented",
      "data-term-stats": [
        "1",
        "0.2",
        "0.000",
        "5240",
        "ol",
        "1"
      ]
    },
    "caustic": {
      "data-frequency": "2030",
      "data-relevance": "83",
      "data-term": "caustic",
      "data-encoded-term": "caustic",
      "data-term-stats": [
        "1",
        "0.2",
        "0.000",
        "2030",
        "ol",
        "1"
      ]
    },
    "uninformed": {
      "data-frequency": "918",
      "data-relevance": "82",
      "data-term": "uninformed",
      "data-encoded-term": "uninformed",
      "data-term-stats": [
        "1",
        "0.2",
        "0.000",
        "918",
        "ol",
        "1"
      ]
    },
    "less": {
      "data-frequency": "368681",
      "data-relevance": "81",
      "data-term": "less",
      "data-encoded-term": "less",
      "data-term-stats": [
        "undefined",
        "0.0",
        "0.000",
        "368681",
        "undefined",
        "undefined"
      ]
    },
    "unrestricted": {
      "data-frequency": "6063",
      "data-relevance": "80",
      "data-term": "unrestricted",
      "data-encoded-term": "unrestricted",
      "data-term-stats": [
        "1",
        "0.2",
        "0.000",
        "6063",
        "ol",
        "1"
      ]
    },
    "unblinking": {
      "data-frequency": "187",
      "data-relevance": "79",
      "data-term": "unblinking",
      "data-encoded-term": "unblinking",
      "data-term-stats": [
        "1",
        "0.2",
        "0.000",
        "187",
        "ol",
        "1"
      ]
    },
    "authentic": {
      "data-frequency": "19194",
      "data-relevance": "78",
      "data-term": "authentic",
      "data-encoded-term": "authentic",
      "data-term-stats": [
        "1",
        "0.2",
        "0.000",
        "19194",
        "ol",
        "1"
      ]
    },
    "nonstop": {
      "data-frequency": "4722",
      "data-relevance": "77",
      "data-term": "nonstop",
      "data-encoded-term": "nonstop",
      "data-term-stats": [
        "1",
        "0.2",
        "0.000",
        "4722",
        "ol",
        "1"
      ]
    },
    "natural": {
      "data-frequency": "351738",
      "data-relevance": "76",
      "data-term": "natural",
      "data-encoded-term": "natural",
      "data-term-stats": [
        "undefined",
        "0.0",
        "0.000",
        "351738",
        "undefined",
        "undefined"
      ]
    },
    "unprocessed": {
      "data-frequency": "678",
      "data-relevance": "75",
      "data-term": "unprocessed",
      "data-encoded-term": "unprocessed",
      "data-term-stats": [
        "undefined",
        "0.0",
        "0.000",
        "678",
        "undefined",
        "undefined"
      ]
    },
    "unboiled": {
      "data-frequency": "-1",
      "data-relevance": "74",
      "data-term": "unboiled",
      "data-encoded-term": "unboiled",
      "data-term-stats": [
        "undefined",
        "0.0",
        "0.000",
        "-1",
        "undefined",
        "undefined"
      ]
    },
    "unobstructed": {
      "data-frequency": "1165",
      "data-relevance": "73",
      "data-term": "unobstructed",
      "data-encoded-term": "unobstructed",
      "data-term-stats": [
        "1",
        "0.2",
        "0.000",
        "1165",
        "ol",
        "1"
      ]
    },
    "illuminating": {
      "data-frequency": "3550",
      "data-relevance": "72",
      "data-term": "illuminating",
      "data-encoded-term": "illuminating",
      "data-term-stats": [
        "1",
        "0.2",
        "0.000",
        "3550",
        "ol",
        "1"
      ]
    },
    "unpolished": {
      "data-frequency": "631",
      "data-relevance": "71",
      "data-term": "unpolished",
      "data-encoded-term": "unpolished",
      "data-term-stats": [
        "1",
        "0.2",
        "0.000",
        "631",
        "ol",
        "1"
      ]
    },
    "genuine": {
      "data-frequency": "22150",
      "data-relevance": "70",
      "data-term": "genuine",
      "data-encoded-term": "genuine",
      "data-term-stats": [
        "1",
        "0.0",
        "0.000",
        "22150",
        "reddit-slashes",
        "1"
      ]
    },
    "unhampered": {
      "data-frequency": "199",
      "data-relevance": "69",
      "data-term": "unhampered",
      "data-encoded-term": "unhampered",
      "data-term-stats": [
        "1",
        "0.2",
        "0.000",
        "199",
        "ol",
        "1"
      ]
    },
    "sweet": {
      "data-frequency": "90399",
      "data-relevance": "68",
      "data-term": "sweet",
      "data-encoded-term": "sweet",
      "data-term-stats": [
        "undefined",
        "0.0",
        "0.000",
        "90399",
        "undefined",
        "undefined"
      ]
    },
    "unphotoshopped": {
      "data-frequency": "-1",
      "data-relevance": "67",
      "data-term": "unphotoshopped",
      "data-encoded-term": "unphotoshopped",
      "data-term-stats": [
        "undefined",
        "0.0",
        "0.000",
        "-1",
        "undefined",
        "undefined"
      ]
    },
    "treated": {
      "data-frequency": "67516",
      "data-relevance": "66",
      "data-term": "treated",
      "data-encoded-term": "treated",
      "data-term-stats": [
        "undefined",
        "0.0",
        "0.000",
        "67516",
        "undefined",
        "undefined"
      ]
    },
    "succinct": {
      "data-frequency": "1137",
      "data-relevance": "65",
      "data-term": "succinct",
      "data-encoded-term": "succinct",
      "data-term-stats": [
        "1",
        "0.2",
        "0.000",
        "1137",
        "ol",
        "1"
      ]
    },
    "unpretentious": {
      "data-frequency": "1103",
      "data-relevance": "64",
      "data-term": "unpretentious",
      "data-encoded-term": "unpretentious",
      "data-term-stats": [
        "1",
        "0.2",
        "0.000",
        "1103",
        "ol",
        "1"
      ]
    },
    "concise": {
      "data-frequency": "29790",
      "data-relevance": "63",
      "data-term": "concise",
      "data-encoded-term": "concise",
      "data-term-stats": [
        "1",
        "0.2",
        "0.000",
        "29790",
        "ol",
        "1"
      ]
    },
    "unrivaled": {
      "data-frequency": "811",
      "data-relevance": "62",
      "data-term": "unrivaled",
      "data-encoded-term": "unrivaled",
      "data-term-stats": [
        "1",
        "0.2",
        "0.000",
        "811",
        "ol",
        "1"
      ]
    },
    "untouched": {
      "data-frequency": "4800",
      "data-relevance": "61",
      "data-term": "untouched",
      "data-encoded-term": "untouched",
      "data-term-stats": [
        "1",
        "0.0",
        "0.000",
        "4800",
        "reddit-slashes",
        "1"
      ]
    },
    "obscure": {
      "data-frequency": "19379",
      "data-relevance": "60",
      "data-term": "obscure",
      "data-encoded-term": "obscure",
      "data-term-stats": [
        "1",
        "0.2",
        "0.000",
        "19379",
        "ol",
        "1"
      ]
    },
    "cloudy": {
      "data-frequency": "9685",
      "data-relevance": "59",
      "data-term": "cloudy",
      "data-encoded-term": "cloudy",
      "data-term-stats": [
        "undefined",
        "0.0",
        "0.000",
        "9685",
        "undefined",
        "undefined"
      ]
    },
    "photoshopped": {
      "data-frequency": "322",
      "data-relevance": "58",
      "data-term": "photoshopped",
      "data-encoded-term": "photoshopped",
      "data-term-stats": [
        "undefined",
        "0.0",
        "0.000",
        "322",
        "undefined",
        "undefined"
      ]
    },
    "tap": {
      "data-frequency": "20734",
      "data-relevance": "57",
      "data-term": "tap",
      "data-encoded-term": "tap",
      "data-term-stats": [
        "undefined",
        "0.0",
        "0.000",
        "20734",
        "undefined",
        "undefined"
      ]
    },
    "unlimited": {
      "data-frequency": "24234",
      "data-relevance": "56",
      "data-term": "unlimited",
      "data-encoded-term": "unlimited",
      "data-term-stats": [
        "undefined",
        "0.0",
        "0.000",
        "24234",
        "undefined",
        "undefined"
      ]
    },
    "real": {
      "data-frequency": "335029",
      "data-relevance": "55",
      "data-term": "real",
      "data-encoded-term": "real",
      "data-term-stats": [
        "undefined",
        "0.0",
        "0.000",
        "335029",
        "undefined",
        "undefined"
      ]
    },
    "unobtrusive": {
      "data-frequency": "1054",
      "data-relevance": "54",
      "data-term": "unobtrusive",
      "data-encoded-term": "unobtrusive",
      "data-term-stats": [
        "1",
        "0.2",
        "0.000",
        "1054",
        "ol",
        "1"
      ]
    },
    "stoppered": {
      "data-frequency": "51",
      "data-relevance": "53",
      "data-term": "stoppered",
      "data-encoded-term": "stoppered",
      "data-term-stats": [
        "1",
        "0.2",
        "0.000",
        "51",
        "ol",
        "1"
      ]
    },
    "lizz winstead": {
      "data-frequency": "51",
      "data-relevance": "52",
      "data-term": "lizz winstead",
      "data-encoded-term": "lizz%20winstead",
      "data-term-stats": [
        "1",
        "0.2",
        "0.000",
        "51",
        "wiki",
        "1"
      ]
    },
    "unbridled": {
      "data-frequency": "1213",
      "data-relevance": "51",
      "data-term": "unbridled",
      "data-encoded-term": "unbridled",
      "data-term-stats": [
        "1",
        "0.2",
        "0.000",
        "1213",
        "ol",
        "1"
      ]
    },
    "unmoderated": {
      "data-frequency": "80",
      "data-relevance": "50",
      "data-term": "unmoderated",
      "data-encoded-term": "unmoderated",
      "data-term-stats": [
        "1",
        "0.1",
        "0.000",
        "80",
        "ol",
        "1"
      ]
    },
    "unmediated": {
      "data-frequency": "170",
      "data-relevance": "49",
      "data-term": "unmediated",
      "data-encoded-term": "unmediated",
      "data-term-stats": [
        "1",
        "0.1",
        "0.000",
        "170",
        "ol",
        "1"
      ]
    },
    "live": {
      "data-frequency": "529392",
      "data-relevance": "48",
      "data-term": "live",
      "data-encoded-term": "live",
      "data-term-stats": [
        "1",
        "0.0",
        "0.000",
        "529392",
        "reddit-slashes",
        "1"
      ]
    },
    "unchecked": {
      "data-frequency": "1624",
      "data-relevance": "47",
      "data-term": "unchecked",
      "data-encoded-term": "unchecked",
      "data-term-stats": [
        "1",
        "0.0",
        "0.000",
        "1624",
        "reddit-slashes",
        "1"
      ]
    },
    "predigested": {
      "data-frequency": "-1",
      "data-relevance": "46",
      "data-term": "predigested",
      "data-encoded-term": "predigested",
      "data-term-stats": [
        "1",
        "0.1",
        "0.000",
        "-1",
        "ol",
        "1"
      ]
    },
    "undrinkable": {
      "data-frequency": "127",
      "data-relevance": "45",
      "data-term": "undrinkable",
      "data-encoded-term": "undrinkable",
      "data-term-stats": [
        "1",
        "0.1",
        "0.000",
        "127",
        "ol",
        "1"
      ]
    },
    "unrehearsed": {
      "data-frequency": "194",
      "data-relevance": "44",
      "data-term": "unrehearsed",
      "data-encoded-term": "unrehearsed",
      "data-term-stats": [
        "1",
        "0.1",
        "0.000",
        "194",
        "ol",
        "1"
      ]
    },
    "unexpurgated": {
      "data-frequency": "227",
      "data-relevance": "43",
      "data-term": "unexpurgated",
      "data-encoded-term": "unexpurgated",
      "data-term-stats": [
        "1",
        "0.1",
        "0.000",
        "227",
        "ol",
        "1"
      ]
    },
    "mixable": {
      "data-frequency": "-1",
      "data-relevance": "42",
      "data-term": "mixable",
      "data-encoded-term": "mixable",
      "data-term-stats": [
        "1",
        "0.1",
        "0.000",
        "-1",
        "ol",
        "1"
      ]
    },
    "unquotable": {
      "data-frequency": "-1",
      "data-relevance": "41",
      "data-term": "unquotable",
      "data-encoded-term": "unquotable",
      "data-term-stats": [
        "1",
        "0.1",
        "0.000",
        "-1",
        "ol",
        "1"
      ]
    },
    "freewheeling": {
      "data-frequency": "622",
      "data-relevance": "40",
      "data-term": "freewheeling",
      "data-encoded-term": "freewheeling",
      "data-term-stats": [
        "1",
        "0.1",
        "0.000",
        "622",
        "ol",
        "1"
      ]
    },
    "unpasteurised": {
      "data-frequency": "77",
      "data-relevance": "39",
      "data-term": "unpasteurised",
      "data-encoded-term": "unpasteurised",
      "data-term-stats": [
        "1",
        "0.1",
        "0.000",
        "77",
        "ol",
        "1"
      ]
    },
    "unenlightening": {
      "data-frequency": "-1",
      "data-relevance": "38",
      "data-term": "unenlightening",
      "data-encoded-term": "unenlightening",
      "data-term-stats": [
        "1",
        "0.1",
        "0.000",
        "-1",
        "ol",
        "1"
      ]
    },
    "uncontrived": {
      "data-frequency": "50",
      "data-relevance": "37",
      "data-term": "uncontrived",
      "data-encoded-term": "uncontrived",
      "data-term-stats": [
        "1",
        "0.1",
        "0.000",
        "50",
        "ol",
        "1"
      ]
    },
    "ineloquent": {
      "data-frequency": "-1",
      "data-relevance": "36",
      "data-term": "ineloquent",
      "data-encoded-term": "ineloquent",
      "data-term-stats": [
        "1",
        "0.1",
        "0.000",
        "-1",
        "ol",
        "1"
      ]
    },
    "sulfurous": {
      "data-frequency": "281",
      "data-relevance": "35",
      "data-term": "sulfurous",
      "data-encoded-term": "sulfurous",
      "data-term-stats": [
        "1",
        "0.1",
        "0.000",
        "281",
        "ol",
        "1"
      ]
    },
    "dusty": {
      "data-frequency": "10946",
      "data-relevance": "34",
      "data-term": "dusty",
      "data-encoded-term": "dusty",
      "data-term-stats": [
        "1",
        "0.0",
        "0.000",
        "10946",
        "reddit-slashes",
        "1"
      ]
    },
    "contentless": {
      "data-frequency": "-1",
      "data-relevance": "33",
      "data-term": "contentless",
      "data-encoded-term": "contentless",
      "data-term-stats": [
        "1",
        "0.1",
        "0.000",
        "-1",
        "ol",
        "1"
      ]
    },
    "filterable": {
      "data-frequency": "57",
      "data-relevance": "32",
      "data-term": "filterable",
      "data-encoded-term": "filterable",
      "data-term-stats": [
        "1",
        "0.1",
        "0.000",
        "57",
        "ol",
        "1"
      ]
    },
    "hemingwayesque": {
      "data-frequency": "-1",
      "data-relevance": "31",
      "data-term": "hemingwayesque",
      "data-encoded-term": "hemingwayesque",
      "data-term-stats": [
        "1",
        "0.1",
        "0.000",
        "-1",
        "ol",
        "1"
      ]
    },
    "fruitiest": {
      "data-frequency": "-1",
      "data-relevance": "30",
      "data-term": "fruitiest",
      "data-encoded-term": "fruitiest",
      "data-term-stats": [
        "1",
        "0.1",
        "0.000",
        "-1",
        "ol",
        "1"
      ]
    },
    "foreshot": {
      "data-frequency": "-1",
      "data-relevance": "29",
      "data-term": "foreshot",
      "data-encoded-term": "foreshot",
      "data-term-stats": [
        "1",
        "0.1",
        "0.000",
        "-1",
        "ol",
        "1"
      ]
    },
    "dispassionate": {
      "data-frequency": "564",
      "data-relevance": "28",
      "data-term": "dispassionate",
      "data-encoded-term": "dispassionate",
      "data-term-stats": [
        "1",
        "0.1",
        "0.000",
        "564",
        "ol",
        "1"
      ]
    },
    "distillable": {
      "data-frequency": "5581",
      "data-relevance": "27",
      "data-term": "distillable",
      "data-encoded-term": "distillable",
      "data-term-stats": [
        "1",
        "0.1",
        "0.000",
        "5581",
        "ol",
        "1"
      ]
    },
    "hyperbolized": {
      "data-frequency": "-1",
      "data-relevance": "26",
      "data-term": "hyperbolized",
      "data-encoded-term": "hyperbolized",
      "data-term-stats": [
        "1",
        "0.1",
        "0.000",
        "-1",
        "ol",
        "1"
      ]
    },
    "comprehendible": {
      "data-frequency": "-1",
      "data-relevance": "25",
      "data-term": "comprehendible",
      "data-encoded-term": "comprehendible",
      "data-term-stats": [
        "1",
        "0.1",
        "0.000",
        "-1",
        "ol",
        "1"
      ]
    },
    "uncolored": {
      "data-frequency": "112",
      "data-relevance": "24",
      "data-term": "uncolored",
      "data-encoded-term": "uncolored",
      "data-term-stats": [
        "1",
        "0.1",
        "0.000",
        "112",
        "ol",
        "1"
      ]
    },
    "unplumbed": {
      "data-frequency": "-1",
      "data-relevance": "23",
      "data-term": "unplumbed",
      "data-encoded-term": "unplumbed",
      "data-term-stats": [
        "1",
        "0.1",
        "0.000",
        "-1",
        "ol",
        "1"
      ]
    },
    "imitable": {
      "data-frequency": "13055",
      "data-relevance": "22",
      "data-term": "imitable",
      "data-encoded-term": "imitable",
      "data-term-stats": [
        "1",
        "0.1",
        "0.000",
        "13055",
        "ol",
        "1"
      ]
    },
    "interactional": {
      "data-frequency": "283",
      "data-relevance": "21",
      "data-term": "interactional",
      "data-encoded-term": "interactional",
      "data-term-stats": [
        "1",
        "0.1",
        "0.000",
        "283",
        "ol",
        "1"
      ]
    },
    "bromidic": {
      "data-frequency": "3770",
      "data-relevance": "20",
      "data-term": "bromidic",
      "data-encoded-term": "bromidic",
      "data-term-stats": [
        "1",
        "0.1",
        "0.000",
        "3770",
        "ol",
        "1"
      ]
    },
    "enlightening": {
      "data-frequency": "1128",
      "data-relevance": "19",
      "data-term": "enlightening",
      "data-encoded-term": "enlightening",
      "data-term-stats": [
        "1",
        "0.1",
        "0.000",
        "1128",
        "ol",
        "1"
      ]
    },
    "unarticulated": {
      "data-frequency": "79",
      "data-relevance": "18",
      "data-term": "unarticulated",
      "data-encoded-term": "unarticulated",
      "data-term-stats": [
        "1",
        "0.1",
        "0.000",
        "79",
        "ol",
        "1"
      ]
    },
    "undogmatic": {
      "data-frequency": "68",
      "data-relevance": "17",
      "data-term": "undogmatic",
      "data-encoded-term": "undogmatic",
      "data-term-stats": [
        "1",
        "0.1",
        "0.000",
        "68",
        "ol",
        "1"
      ]
    },
    "unbeholden": {
      "data-frequency": "-1",
      "data-relevance": "16",
      "data-term": "unbeholden",
      "data-encoded-term": "unbeholden",
      "data-term-stats": [
        "1",
        "0.1",
        "0.000",
        "-1",
        "ol",
        "1"
      ]
    },
    "unembellished": {
      "data-frequency": "68",
      "data-relevance": "15",
      "data-term": "unembellished",
      "data-encoded-term": "unembellished",
      "data-term-stats": [
        "1",
        "0.1",
        "0.000",
        "68",
        "ol",
        "1"
      ]
    },
    "placeless": {
      "data-frequency": "54",
      "data-relevance": "14",
      "data-term": "placeless",
      "data-encoded-term": "placeless",
      "data-term-stats": [
        "1",
        "0.1",
        "0.000",
        "54",
        "ol",
        "1"
      ]
    },
    "undistorted": {
      "data-frequency": "174",
      "data-relevance": "13",
      "data-term": "undistorted",
      "data-encoded-term": "undistorted",
      "data-term-stats": [
        "1",
        "0.1",
        "0.000",
        "174",
        "ol",
        "1"
      ]
    },
    "glug": {
      "data-frequency": "77",
      "data-relevance": "12",
      "data-term": "glug",
      "data-encoded-term": "glug",
      "data-term-stats": [
        "1",
        "0.1",
        "0.000",
        "77",
        "ol",
        "1"
      ]
    },
    "skunky": {
      "data-frequency": "45",
      "data-relevance": "11",
      "data-term": "skunky",
      "data-encoded-term": "skunky",
      "data-term-stats": [
        "1",
        "0.1",
        "0.000",
        "45",
        "ol",
        "1"
      ]
    },
    "unsweet": {
      "data-frequency": "-1",
      "data-relevance": "10",
      "data-term": "unsweet",
      "data-encoded-term": "unsweet",
      "data-term-stats": [
        "1",
        "0.1",
        "0.000",
        "-1",
        "ol",
        "1"
      ]
    },
    "expressional": {
      "data-frequency": "49",
      "data-relevance": "9",
      "data-term": "expressional",
      "data-encoded-term": "expressional",
      "data-term-stats": [
        "1",
        "0.1",
        "0.000",
        "49",
        "ol",
        "1"
      ]
    },
    "chuck d": {
      "data-frequency": "25034",
      "data-relevance": "8",
      "data-term": "chuck d",
      "data-encoded-term": "chuck%20d",
      "data-term-stats": [
        "1",
        "0.1",
        "0.000",
        "25034",
        "wiki",
        "1"
      ]
    },
    "longwinded": {
      "data-frequency": "-1",
      "data-relevance": "7",
      "data-term": "longwinded",
      "data-encoded-term": "longwinded",
      "data-term-stats": [
        "1",
        "0.1",
        "0.000",
        "-1",
        "ol",
        "1"
      ]
    },
    "draught beer": {
      "data-frequency": "117",
      "data-relevance": "6",
      "data-term": "draught beer",
      "data-encoded-term": "draught%20beer",
      "data-term-stats": [
        "1",
        "-0.1",
        "0.000",
        "117",
        "ol",
        "1"
      ]
    },
    "filter tip": {
      "data-frequency": "-1",
      "data-relevance": "5",
      "data-term": "filter tip",
      "data-encoded-term": "filter%20tip",
      "data-term-stats": [
        "1",
        "-0.1",
        "0.000",
        "-1",
        "ol",
        "1"
      ]
    },
    "corn liquor": {
      "data-frequency": "978",
      "data-relevance": "4",
      "data-term": "corn liquor",
      "data-encoded-term": "corn%20liquor",
      "data-term-stats": [
        "1",
        "-0.1",
        "0.000",
        "978",
        "ol",
        "1"
      ]
    },
    "draft beer": {
      "data-frequency": "116",
      "data-relevance": "3",
      "data-term": "draft beer",
      "data-encoded-term": "draft%20beer",
      "data-term-stats": [
        "1",
        "-0.1",
        "0.000",
        "116",
        "ol",
        "1"
      ]
    },
    "the karminsky experience": {
      "data-frequency": "-1",
      "data-relevance": "2",
      "data-term": "the karminsky experience",
      "data-encoded-term": "the%20karminsky%20experience",
      "data-term-stats": [
        "1",
        "-0.1",
        "0.000",
        "-1",
        "wiki",
        "1"
      ]
    },
    "the huffington post": {
      "data-frequency": "30148",
      "data-relevance": "1",
      "data-term": "the huffington post",
      "data-encoded-term": "the%20huffington%20post",
      "data-term-stats": [
        "1",
        "-0.3",
        "0.000",
        "30148",
        "wiki",
        "1"
      ]
    },
    "jerry springer": {
      "data-frequency": "916",
      "data-relevance": "0",
      "data-term": "jerry springer",
      "data-encoded-term": "jerry%20springer",
      "data-term-stats": [
        "1",
        "-0.2",
        "0.000",
        "916",
        "wiki",
        "1"
      ]
    }
  },
  "related_ngsl": {},
  "related_awl_economics": {},
  "related_awl_computer_science_s": {},
  "related_awl_computer_science": {},
  "irregular_words": {},
  "plurals": {},
  "gerunds": {},
  "wooordhunt": {
    "similar_words": [
      "filter",
      "filtering",
      "filtered"
    ],
    "word_forms": [],
    "examples": [
      {
        "en": "Port is bottled unfiltered, and sealed with a cork.",
        "ru": "Портвейн разливают в нефильтрованные бутылки и закупоривают пробкой."
      },
      {
        "en": "He took an unfiltered cigarette out of his pocket and lit it.",
        "ru": "Он достал из кармана сигарету без фильтра и закурил."
      },
      {
        "en": "The radio station provides millions of people with unfiltered news.",
        "ru": "Радиостанция предоставляет миллионам людей нефильтрованные новости."
      },
      {
        "en": "One million people have been affected by having unfiltered water supplies.",
        "ru": "Один миллион человек пострадал из-за наличия нефильтрованного водоснабжения."
      }
    ]
  },
  "custom_words": [],
  "important_word": {
    "word_forms": [
      "uninfiltrated"
    ],
    "synonyms": [],
    "antonyms": [
      "filtered"
    ],
    "similar_terms": [
      "filtering",
      "filter",
      "filtered"
    ],
    "gerunds": [],
    "irregular_words": [],
    "relatedwords": [
      "unvarnished",
      "unadulterated",
      "uncut",
      "filter",
      "undiluted",
      "unedited",
      "filtered",
      "untainted",
      "direct",
      "uncensored",
      "woodbine",
      "raw"
    ]
  }
}